{
"meta":{"test_sets":[],"test_metrics":[],"learn_metrics":[{"best_value":"Min","name":"RMSE"}],"launch_mode":"Train","parameters":"","iteration_count":1000,"learn_sets":["learn"],"name":"experiment"},
"iterations":[
{"learn":[14.59871775],"iteration":0,"passed_time":0.002369143452,"remaining_time":2.366774309},
{"learn":[14.22518863],"iteration":1,"passed_time":0.004533487457,"remaining_time":2.262210241},
{"learn":[13.8866124],"iteration":2,"passed_time":0.007632103035,"remaining_time":2.536402242},
{"learn":[13.52356875],"iteration":3,"passed_time":0.01129143413,"remaining_time":2.811567099},
{"learn":[13.18870211],"iteration":4,"passed_time":0.01336522804,"remaining_time":2.65968038},
{"learn":[12.9124226],"iteration":5,"passed_time":0.01528085566,"remaining_time":2.531528421},
{"learn":[12.60003351],"iteration":6,"passed_time":0.01694719078,"remaining_time":2.404080064},
{"learn":[12.32990573],"iteration":7,"passed_time":0.01872321843,"remaining_time":2.321679085},
{"learn":[12.0660619],"iteration":8,"passed_time":0.02091805014,"remaining_time":2.303309743},
{"learn":[11.77309809],"iteration":9,"passed_time":0.02358245246,"remaining_time":2.334662793},
{"learn":[11.49227636],"iteration":10,"passed_time":0.02605345967,"remaining_time":2.342442874},
{"learn":[11.26264833],"iteration":11,"passed_time":0.02772025484,"remaining_time":2.282300982},
{"learn":[11.04260393],"iteration":12,"passed_time":0.02919426388,"remaining_time":2.216518342},
{"learn":[10.79916926],"iteration":13,"passed_time":0.03088352583,"remaining_time":2.175082605},
{"learn":[10.5541002],"iteration":14,"passed_time":0.03233359559,"remaining_time":2.123239444},
{"learn":[10.31918115],"iteration":15,"passed_time":0.03385229151,"remaining_time":2.081915928},
{"learn":[10.10004441],"iteration":16,"passed_time":0.03610678005,"remaining_time":2.087821458},
{"learn":[9.894556723],"iteration":17,"passed_time":0.03876762176,"remaining_time":2.114989143},
{"learn":[9.690174082],"iteration":18,"passed_time":0.04120103918,"remaining_time":2.127274707},
{"learn":[9.506034866],"iteration":19,"passed_time":0.04269397435,"remaining_time":2.092004743},
{"learn":[9.338524633],"iteration":20,"passed_time":0.04412689621,"remaining_time":2.057153876},
{"learn":[9.170203312],"iteration":21,"passed_time":0.04590970107,"remaining_time":2.040894893},
{"learn":[9.010299969],"iteration":22,"passed_time":0.0475065382,"remaining_time":2.017995123},
{"learn":[8.843866678],"iteration":23,"passed_time":0.04900913817,"remaining_time":1.993038286},
{"learn":[8.690548059],"iteration":24,"passed_time":0.05103093555,"remaining_time":1.990206487},
{"learn":[8.555307687],"iteration":25,"passed_time":0.05348498288,"remaining_time":2.003629743},
{"learn":[8.413851302],"iteration":26,"passed_time":0.05602070913,"remaining_time":2.01882037},
{"learn":[8.29256019],"iteration":27,"passed_time":0.05747790178,"remaining_time":1.995304305},
{"learn":[8.162193833],"iteration":28,"passed_time":0.05880296758,"remaining_time":1.96888557},
{"learn":[8.040736294],"iteration":29,"passed_time":0.06008271258,"remaining_time":1.942674373},
{"learn":[7.921220278],"iteration":30,"passed_time":0.06185380362,"remaining_time":1.933430184},
{"learn":[7.809589039],"iteration":31,"passed_time":0.06423470582,"remaining_time":1.943099851},
{"learn":[7.699675801],"iteration":32,"passed_time":0.06602176137,"remaining_time":1.934637674},
{"learn":[7.60645267],"iteration":33,"passed_time":0.06804826117,"remaining_time":1.933371185},
{"learn":[7.498880302],"iteration":34,"passed_time":0.07058999429,"remaining_time":1.946266985},
{"learn":[7.401158744],"iteration":35,"passed_time":0.07199742619,"remaining_time":1.927931079},
{"learn":[7.306431077],"iteration":36,"passed_time":0.07325158347,"remaining_time":1.906520943},
{"learn":[7.223863468],"iteration":37,"passed_time":0.07458356292,"remaining_time":1.888141777},
{"learn":[7.143477682],"iteration":38,"passed_time":0.07623490606,"remaining_time":1.878506275},
{"learn":[7.062817131],"iteration":39,"passed_time":0.07832369612,"remaining_time":1.879768707},
{"learn":[6.990793435],"iteration":40,"passed_time":0.07994342388,"remaining_time":1.869896183},
{"learn":[6.931862224],"iteration":41,"passed_time":0.08210210169,"remaining_time":1.872709843},
{"learn":[6.858296558],"iteration":42,"passed_time":0.08527695172,"remaining_time":1.897907972},
{"learn":[6.786268161],"iteration":43,"passed_time":0.08701593116,"remaining_time":1.890618868},
{"learn":[6.717118549],"iteration":44,"passed_time":0.08838650744,"remaining_time":1.875758102},
{"learn":[6.652948106],"iteration":45,"passed_time":0.08995321042,"remaining_time":1.865551364},
{"learn":[6.589686076],"iteration":46,"passed_time":0.09149013157,"remaining_time":1.855108413},
{"learn":[6.531283097],"iteration":47,"passed_time":0.09285425092,"remaining_time":1.84160931},
{"learn":[6.471368031],"iteration":48,"passed_time":0.09424525702,"remaining_time":1.829127335},
{"learn":[6.416481395],"iteration":49,"passed_time":0.09607226584,"remaining_time":1.825373051},
{"learn":[6.369870822],"iteration":50,"passed_time":0.09826727392,"remaining_time":1.828542019},
{"learn":[6.325678067],"iteration":51,"passed_time":0.1005096061,"remaining_time":1.832367434},
{"learn":[6.275766122],"iteration":52,"passed_time":0.1018220483,"remaining_time":1.819348675},
{"learn":[6.224773967],"iteration":53,"passed_time":0.1031288718,"remaining_time":1.806665051},
{"learn":[6.182249254],"iteration":54,"passed_time":0.1057354708,"remaining_time":1.816727635},
{"learn":[6.139904173],"iteration":55,"passed_time":0.1079022482,"remaining_time":1.818923613},
{"learn":[6.100525536],"iteration":56,"passed_time":0.1096204064,"remaining_time":1.813544618},
{"learn":[6.062568564],"iteration":57,"passed_time":0.1140473872,"remaining_time":1.852286874},
{"learn":[6.030559288],"iteration":58,"passed_time":0.1162918548,"remaining_time":1.854756532},
{"learn":[5.997931376],"iteration":59,"passed_time":0.1177661488,"remaining_time":1.845002998},
{"learn":[5.964103835],"iteration":60,"passed_time":0.1191623232,"remaining_time":1.834318385},
{"learn":[5.933729724],"iteration":61,"passed_time":0.1208742262,"remaining_time":1.828710067},
{"learn":[5.901932711],"iteration":62,"passed_time":0.1223487123,"remaining_time":1.819694341},
{"learn":[5.873727795],"iteration":63,"passed_time":0.1237145288,"remaining_time":1.809324984},
{"learn":[5.846485734],"iteration":64,"passed_time":0.1250044993,"remaining_time":1.798141644},
{"learn":[5.820630862],"iteration":65,"passed_time":0.1264993496,"remaining_time":1.790157462},
{"learn":[5.793646238],"iteration":66,"passed_time":0.1285575504,"remaining_time":1.790211859},
{"learn":[5.765388646],"iteration":67,"passed_time":0.1310450912,"remaining_time":1.796088602},
{"learn":[5.747073912],"iteration":68,"passed_time":0.1326214777,"remaining_time":1.789428923},
{"learn":[5.722315217],"iteration":69,"passed_time":0.1341582179,"remaining_time":1.782387752},
{"learn":[5.699970599],"iteration":70,"passed_time":0.1357531175,"remaining_time":1.776262622},
{"learn":[5.682732647],"iteration":71,"passed_time":0.1371684247,"remaining_time":1.767948585},
{"learn":[5.663525791],"iteration":72,"passed_time":0.1385624249,"remaining_time":1.759552985},
{"learn":[5.642381613],"iteration":73,"passed_time":0.1399073086,"remaining_time":1.750731997},
{"learn":[5.621404779],"iteration":74,"passed_time":0.141501437,"remaining_time":1.74518439},
{"learn":[5.602460129],"iteration":75,"passed_time":0.1432406465,"remaining_time":1.741504702},
{"learn":[5.587337574],"iteration":76,"passed_time":0.1447255287,"remaining_time":1.734826792},
{"learn":[5.572393026],"iteration":77,"passed_time":0.1468470235,"remaining_time":1.735807124},
{"learn":[5.558425806],"iteration":78,"passed_time":0.1483576819,"remaining_time":1.729587658},
{"learn":[5.541518902],"iteration":79,"passed_time":0.1499618374,"remaining_time":1.72456113},
{"learn":[5.526157283],"iteration":80,"passed_time":0.1514832911,"remaining_time":1.718680797},
{"learn":[5.511746977],"iteration":81,"passed_time":0.1528489636,"remaining_time":1.711162788},
{"learn":[5.504975022],"iteration":82,"passed_time":0.1536201423,"remaining_time":1.697224946},
{"learn":[5.493980522],"iteration":83,"passed_time":0.1551015263,"remaining_time":1.691345215},
{"learn":[5.480745463],"iteration":84,"passed_time":0.1590040428,"remaining_time":1.711631755},
{"learn":[5.464052013],"iteration":85,"passed_time":0.1613448062,"remaining_time":1.714757591},
{"learn":[5.449143727],"iteration":86,"passed_time":0.1632673778,"remaining_time":1.713369149},
{"learn":[5.438255432],"iteration":87,"passed_time":0.1650336658,"remaining_time":1.7103489},
{"learn":[5.425927931],"iteration":88,"passed_time":0.1665649116,"remaining_time":1.704950949},
{"learn":[5.412331217],"iteration":89,"passed_time":0.1680468426,"remaining_time":1.699140297},
{"learn":[5.400691499],"iteration":90,"passed_time":0.1694645029,"remaining_time":1.692782782},
{"learn":[5.391618744],"iteration":91,"passed_time":0.1722673455,"remaining_time":1.700203801},
{"learn":[5.380766572],"iteration":92,"passed_time":0.1739379192,"remaining_time":1.696362288},
{"learn":[5.372207183],"iteration":93,"passed_time":0.177598744,"remaining_time":1.711749597},
{"learn":[5.362918837],"iteration":94,"passed_time":0.1796330439,"remaining_time":1.711241102},
{"learn":[5.348292324],"iteration":95,"passed_time":0.1812833164,"remaining_time":1.707084562},
{"learn":[5.339772295],"iteration":96,"passed_time":0.1827068625,"remaining_time":1.70086904},
{"learn":[5.331515983],"iteration":97,"passed_time":0.1843258611,"remaining_time":1.696550273},
{"learn":[5.323861644],"iteration":98,"passed_time":0.1860553238,"remaining_time":1.693291381},
{"learn":[5.313277281],"iteration":99,"passed_time":0.1884031485,"remaining_time":1.695628337},
{"learn":[5.30685627],"iteration":100,"passed_time":0.1906512588,"remaining_time":1.696984967},
{"learn":[5.29652059],"iteration":101,"passed_time":0.1933096193,"remaining_time":1.701882727},
{"learn":[5.288350766],"iteration":102,"passed_time":0.1964861489,"remaining_time":1.711146365},
{"learn":[5.27993346],"iteration":103,"passed_time":0.1988114928,"remaining_time":1.712837476},
{"learn":[5.271789139],"iteration":104,"passed_time":0.2007556814,"remaining_time":1.711203189},
{"learn":[5.262684686],"iteration":105,"passed_time":0.2032233089,"remaining_time":1.713977718},
{"learn":[5.251619772],"iteration":106,"passed_time":0.2051382743,"remaining_time":1.712041859},
{"learn":[5.241012171],"iteration":107,"passed_time":0.2076081971,"remaining_time":1.714689924},
{"learn":[5.232684032],"iteration":108,"passed_time":0.2093212952,"remaining_time":1.71105756},
{"learn":[5.224267141],"iteration":109,"passed_time":0.2109519951,"remaining_time":1.706793415},
{"learn":[5.216324968],"iteration":110,"passed_time":0.2125814534,"remaining_time":1.702566775},
{"learn":[5.211102527],"iteration":111,"passed_time":0.2140573891,"remaining_time":1.6971693},
{"learn":[5.206364257],"iteration":112,"passed_time":0.2155200371,"remaining_time":1.691736928},
{"learn":[5.196937641],"iteration":113,"passed_time":0.2174471115,"remaining_time":1.689983691},
{"learn":[5.190746047],"iteration":114,"passed_time":0.2211248854,"remaining_time":1.701700205},
{"learn":[5.181885213],"iteration":115,"passed_time":0.22458743,"remaining_time":1.711511105},
{"learn":[5.178293568],"iteration":116,"passed_time":0.2260251463,"remaining_time":1.705813711},
{"learn":[5.170991438],"iteration":117,"passed_time":0.2275805352,"remaining_time":1.701068068},
{"learn":[5.166257212],"iteration":118,"passed_time":0.2290948082,"remaining_time":1.696071647},
{"learn":[5.161421246],"iteration":119,"passed_time":0.2305572893,"remaining_time":1.690753455},
{"learn":[5.158223542],"iteration":120,"passed_time":0.2328360096,"remaining_time":1.691428532},
{"learn":[5.15470988],"iteration":121,"passed_time":0.234210124,"remaining_time":1.685544991},
{"learn":[5.146388143],"iteration":122,"passed_time":0.2370239383,"remaining_time":1.68999995},
{"learn":[5.139529364],"iteration":123,"passed_time":0.2398924005,"remaining_time":1.694723733},
{"learn":[5.134276023],"iteration":124,"passed_time":0.241347253,"remaining_time":1.689430771},
{"learn":[5.128536065],"iteration":125,"passed_time":0.24300096,"remaining_time":1.685578088},
{"learn":[5.123300353],"iteration":126,"passed_time":0.2458418832,"remaining_time":1.689920977},
{"learn":[5.116200518],"iteration":127,"passed_time":0.2475208294,"remaining_time":1.68623565},
{"learn":[5.108728704],"iteration":128,"passed_time":0.2491778607,"remaining_time":1.682433463},
{"learn":[5.104075866],"iteration":129,"passed_time":0.2526564515,"remaining_time":1.690854714},
{"learn":[5.100317606],"iteration":130,"passed_time":0.2552127481,"remaining_time":1.692976169},
{"learn":[5.095814182],"iteration":131,"passed_time":0.2567402071,"remaining_time":1.688261362},
{"learn":[5.092146915],"iteration":132,"passed_time":0.2582493209,"remaining_time":1.683474897},
{"learn":[5.085258329],"iteration":133,"passed_time":0.2599202474,"remaining_time":1.679783092},
{"learn":[5.079219421],"iteration":134,"passed_time":0.2629997401,"remaining_time":1.685146483},
{"learn":[5.076476829],"iteration":135,"passed_time":0.2649926101,"remaining_time":1.683482464},
{"learn":[5.072133867],"iteration":136,"passed_time":0.2665483484,"remaining_time":1.679060034},
{"learn":[5.067031564],"iteration":137,"passed_time":0.2697675134,"remaining_time":1.68506954},
{"learn":[5.061358312],"iteration":138,"passed_time":0.2717735992,"remaining_time":1.68343215},
{"learn":[5.056759124],"iteration":139,"passed_time":0.2735550813,"remaining_time":1.680409785},
{"learn":[5.050254],"iteration":140,"passed_time":0.2755373867,"remaining_time":1.678628477},
{"learn":[5.048376474],"iteration":141,"passed_time":0.2766333885,"remaining_time":1.671489066},
{"learn":[5.042603751],"iteration":142,"passed_time":0.2798199499,"remaining_time":1.676962916},
{"learn":[5.037477349],"iteration":143,"passed_time":0.282571511,"remaining_time":1.679730649},
{"learn":[5.03230489],"iteration":144,"passed_time":0.2877791984,"remaining_time":1.696904928},
{"learn":[5.025976187],"iteration":145,"passed_time":0.2894720787,"remaining_time":1.693213392},
{"learn":[5.01952451],"iteration":146,"passed_time":0.2912019412,"remaining_time":1.689763645},
{"learn":[5.017569424],"iteration":147,"passed_time":0.2930866734,"remaining_time":1.687228688},
{"learn":[5.008962367],"iteration":148,"passed_time":0.2958176907,"remaining_time":1.689535938},
{"learn":[5.003880266],"iteration":149,"passed_time":0.2987875887,"remaining_time":1.693129669},
{"learn":[4.996387564],"iteration":150,"passed_time":0.3013423534,"remaining_time":1.694302371},
{"learn":[4.993361683],"iteration":151,"passed_time":0.3033973048,"remaining_time":1.692637595},
{"learn":[4.99005752],"iteration":152,"passed_time":0.3055823124,"remaining_time":1.691687703},
{"learn":[4.986908764],"iteration":153,"passed_time":0.3075675998,"remaining_time":1.689624607},
{"learn":[4.985207175],"iteration":154,"passed_time":0.3102998429,"remaining_time":1.691634627},
{"learn":[4.979003494],"iteration":155,"passed_time":0.3122754643,"remaining_time":1.689490332},
{"learn":[4.973142217],"iteration":156,"passed_time":0.3154229138,"remaining_time":1.693640232},
{"learn":[4.967056696],"iteration":157,"passed_time":0.3182094517,"remaining_time":1.69577442},
{"learn":[4.961460696],"iteration":158,"passed_time":0.3199639393,"remaining_time":1.69238788},
{"learn":[4.954240363],"iteration":159,"passed_time":0.3217560454,"remaining_time":1.689219239},
{"learn":[4.952320707],"iteration":160,"passed_time":0.3231016642,"remaining_time":1.68374097},
{"learn":[4.948337777],"iteration":161,"passed_time":0.3261548845,"remaining_time":1.687146872},
{"learn":[4.943228639],"iteration":162,"passed_time":0.3304371573,"remaining_time":1.696784667},
{"learn":[4.938545759],"iteration":163,"passed_time":0.3333862764,"remaining_time":1.699456873},
{"learn":[4.935330572],"iteration":164,"passed_time":0.3352551457,"remaining_time":1.696594222},
{"learn":[4.932051543],"iteration":165,"passed_time":0.3371128997,"remaining_time":1.693687701},
{"learn":[4.928964153],"iteration":166,"passed_time":0.3421619171,"remaining_time":1.706711838},
{"learn":[4.922860227],"iteration":167,"passed_time":0.3450271589,"remaining_time":1.70870593},
{"learn":[4.917668772],"iteration":168,"passed_time":0.3471062238,"remaining_time":1.706776757},
{"learn":[4.910365386],"iteration":169,"passed_time":0.3488294492,"remaining_time":1.703108487},
{"learn":[4.906457206],"iteration":170,"passed_time":0.3507994044,"remaining_time":1.700659101},
{"learn":[4.901996508],"iteration":171,"passed_time":0.352380188,"remaining_time":1.696341835},
{"learn":[4.896816173],"iteration":172,"passed_time":0.3541236116,"remaining_time":1.692833681},
{"learn":[4.891123132],"iteration":173,"passed_time":0.3563980957,"remaining_time":1.691866822},
{"learn":[4.887630202],"iteration":174,"passed_time":0.3617972111,"remaining_time":1.705615424},
{"learn":[4.885259712],"iteration":175,"passed_time":0.3635834276,"remaining_time":1.702231502},
{"learn":[4.880659728],"iteration":176,"passed_time":0.3651332052,"remaining_time":1.697766259},
{"learn":[4.877299723],"iteration":177,"passed_time":0.3669342374,"remaining_time":1.694494063},
{"learn":[4.874038772],"iteration":178,"passed_time":0.3692998415,"remaining_time":1.693827765},
{"learn":[4.86943698],"iteration":179,"passed_time":0.3739929582,"remaining_time":1.703745698},
{"learn":[4.861268711],"iteration":180,"passed_time":0.3760194613,"remaining_time":1.701436126},
{"learn":[4.858673056],"iteration":181,"passed_time":0.3777547545,"remaining_time":1.69782082},
{"learn":[4.854036207],"iteration":182,"passed_time":0.3791377638,"remaining_time":1.692653295},
{"learn":[4.85130244],"iteration":183,"passed_time":0.3804941854,"remaining_time":1.687408996},
{"learn":[4.847510084],"iteration":184,"passed_time":0.3819397512,"remaining_time":1.682599444},
{"learn":[4.845691673],"iteration":185,"passed_time":0.3847679905,"remaining_time":1.68387712},
{"learn":[4.842058646],"iteration":186,"passed_time":0.386769668,"remaining_time":1.681517327},
{"learn":[4.838623675],"iteration":187,"passed_time":0.3900817724,"remaining_time":1.684821272},
{"learn":[4.834602161],"iteration":188,"passed_time":0.3916154907,"remaining_time":1.680424143},
{"learn":[4.830858976],"iteration":189,"passed_time":0.3931351121,"remaining_time":1.675997057},
{"learn":[4.827590511],"iteration":190,"passed_time":0.3947168487,"remaining_time":1.671863511},
{"learn":[4.822246226],"iteration":191,"passed_time":0.396316924,"remaining_time":1.667833722},
{"learn":[4.816686395],"iteration":192,"passed_time":0.3980091214,"remaining_time":1.664214306},
{"learn":[4.814797121],"iteration":193,"passed_time":0.4000419987,"remaining_time":1.662030159},
{"learn":[4.811639392],"iteration":194,"passed_time":0.4018836559,"remaining_time":1.659058169},
{"learn":[4.804813432],"iteration":195,"passed_time":0.4047686916,"remaining_time":1.660377694},
{"learn":[4.80251613],"iteration":196,"passed_time":0.4067813428,"remaining_time":1.65809857},
{"learn":[4.800087884],"iteration":197,"passed_time":0.408332855,"remaining_time":1.653954292},
{"learn":[4.794773135],"iteration":198,"passed_time":0.4097802697,"remaining_time":1.649417066},
{"learn":[4.791664833],"iteration":199,"passed_time":0.4114958361,"remaining_time":1.645983344},
{"learn":[4.785989873],"iteration":200,"passed_time":0.4130396988,"remaining_time":1.641884176},
{"learn":[4.782387142],"iteration":201,"passed_time":0.416614794,"remaining_time":1.645834681},
{"learn":[4.778623704],"iteration":202,"passed_time":0.4193061147,"remaining_time":1.646241248},
{"learn":[4.775772178],"iteration":203,"passed_time":0.4214018991,"remaining_time":1.644293685},
{"learn":[4.77023101],"iteration":204,"passed_time":0.4231451417,"remaining_time":1.640977501},
{"learn":[4.764496689],"iteration":205,"passed_time":0.4252847312,"remaining_time":1.639204255},
{"learn":[4.763138716],"iteration":206,"passed_time":0.4275448281,"remaining_time":1.637889124},
{"learn":[4.758053283],"iteration":207,"passed_time":0.4301560475,"remaining_time":1.637901873},
{"learn":[4.755063788],"iteration":208,"passed_time":0.4347977234,"remaining_time":1.645574159},
{"learn":[4.752465267],"iteration":209,"passed_time":0.4374580893,"remaining_time":1.645675669},
{"learn":[4.748067377],"iteration":210,"passed_time":0.4397529807,"remaining_time":1.644384369},
{"learn":[4.744163298],"iteration":211,"passed_time":0.4415720555,"remaining_time":1.641314999},
{"learn":[4.736670896],"iteration":212,"passed_time":0.443130268,"remaining_time":1.637293525},
{"learn":[4.73349255],"iteration":213,"passed_time":0.4450078208,"remaining_time":1.634467977},
{"learn":[4.731864595],"iteration":214,"passed_time":0.4486752635,"remaining_time":1.638186427},
{"learn":[4.728398311],"iteration":215,"passed_time":0.4506519971,"remaining_time":1.635699841},
{"learn":[4.723865975],"iteration":216,"passed_time":0.4522261167,"remaining_time":1.631765204},
{"learn":[4.723483365],"iteration":217,"passed_time":0.4538080795,"remaining_time":1.627880359},
{"learn":[4.72095416],"iteration":218,"passed_time":0.4554274625,"remaining_time":1.624149992},
{"learn":[4.716173382],"iteration":219,"passed_time":0.4568934243,"remaining_time":1.619894868},
{"learn":[4.710563974],"iteration":220,"passed_time":0.4583084255,"remaining_time":1.615485355},
{"learn":[4.707160263],"iteration":221,"passed_time":0.4604583103,"remaining_time":1.613678223},
{"learn":[4.70408351],"iteration":222,"passed_time":0.463491716,"remaining_time":1.614946472},
{"learn":[4.702501831],"iteration":223,"passed_time":0.4651503888,"remaining_time":1.611413847},
{"learn":[4.700269738],"iteration":224,"passed_time":0.466758399,"remaining_time":1.607723374},
{"learn":[4.695346302],"iteration":225,"passed_time":0.468725808,"remaining_time":1.605282192},
{"learn":[4.689769299],"iteration":226,"passed_time":0.4701519826,"remaining_time":1.601002126},
{"learn":[4.687919514],"iteration":227,"passed_time":0.4717856479,"remaining_time":1.59744965},
{"learn":[4.682982074],"iteration":228,"passed_time":0.4733413538,"remaining_time":1.593651458},
{"learn":[4.679578702],"iteration":229,"passed_time":0.4749997391,"remaining_time":1.590216518},
{"learn":[4.675751423],"iteration":230,"passed_time":0.4771767399,"remaining_time":1.588523433},
{"learn":[4.672710726],"iteration":231,"passed_time":0.4790634051,"remaining_time":1.585865065},
{"learn":[4.6690533],"iteration":232,"passed_time":0.480482976,"remaining_time":1.581675719},
{"learn":[4.667595702],"iteration":233,"passed_time":0.4819626325,"remaining_time":1.577706737},
{"learn":[4.664241291],"iteration":234,"passed_time":0.4835452159,"remaining_time":1.574094001},
{"learn":[4.662246999],"iteration":235,"passed_time":0.4850133371,"remaining_time":1.570127922},
{"learn":[4.658668443],"iteration":236,"passed_time":0.4865676333,"remaining_time":1.566460355},
{"learn":[4.658017572],"iteration":237,"passed_time":0.4882028089,"remaining_time":1.563069497},
{"learn":[4.657656705],"iteration":238,"passed_time":0.4897229494,"remaining_time":1.559327048},
{"learn":[4.653242871],"iteration":239,"passed_time":0.4917526213,"remaining_time":1.557216634},
{"learn":[4.6507302],"iteration":240,"passed_time":0.4934812692,"remaining_time":1.554158852},
{"learn":[4.647671336],"iteration":241,"passed_time":0.4950889212,"remaining_time":1.550733067},
{"learn":[4.645506007],"iteration":242,"passed_time":0.4966482967,"remaining_time":1.547171854},
{"learn":[4.641297906],"iteration":243,"passed_time":0.4982892525,"remaining_time":1.543879815},
{"learn":[4.63798107],"iteration":244,"passed_time":0.4996691192,"remaining_time":1.539796674},
{"learn":[4.635062318],"iteration":245,"passed_time":0.5011411866,"remaining_time":1.536018108},
{"learn":[4.631606017],"iteration":246,"passed_time":0.5027689353,"remaining_time":1.532732827},
{"learn":[4.630215494],"iteration":247,"passed_time":0.5041272736,"remaining_time":1.528643991},
{"learn":[4.62729814],"iteration":248,"passed_time":0.505901419,"remaining_time":1.525831188},
{"learn":[4.624691756],"iteration":249,"passed_time":0.5086058961,"remaining_time":1.525817688},
{"learn":[4.621840053],"iteration":250,"passed_time":0.5101992837,"remaining_time":1.522467185},
{"learn":[4.619602091],"iteration":251,"passed_time":0.5131656838,"remaining_time":1.523206077},
{"learn":[4.613584029],"iteration":252,"passed_time":0.5149778192,"remaining_time":1.520507632},
{"learn":[4.6119388],"iteration":253,"passed_time":0.5166649905,"remaining_time":1.517449145},
{"learn":[4.60870702],"iteration":254,"passed_time":0.5184677884,"remaining_time":1.514739225},
{"learn":[4.604771557],"iteration":255,"passed_time":0.5199497548,"remaining_time":1.511103975},
{"learn":[4.604231277],"iteration":256,"passed_time":0.5241725159,"remaining_time":1.515409258},
{"learn":[4.600750354],"iteration":257,"passed_time":0.5265037189,"remaining_time":1.51420837},
{"learn":[4.596488253],"iteration":258,"passed_time":0.5283368748,"remaining_time":1.511573839},
{"learn":[4.59470784],"iteration":259,"passed_time":0.5302028681,"remaining_time":1.509038932},
{"learn":[4.588818005],"iteration":260,"passed_time":0.53200382,"remaining_time":1.506324992},
{"learn":[4.585054174],"iteration":261,"passed_time":0.5336731367,"remaining_time":1.503247233},
{"learn":[4.581471435],"iteration":262,"passed_time":0.5351630217,"remaining_time":1.499677365},
{"learn":[4.577555199],"iteration":263,"passed_time":0.538215304,"remaining_time":1.500479029},
{"learn":[4.57457145],"iteration":264,"passed_time":0.5396478041,"remaining_time":1.496759004},
{"learn":[4.573029224],"iteration":265,"passed_time":0.5414114503,"remaining_time":1.493969942},
{"learn":[4.571326203],"iteration":266,"passed_time":0.5430751903,"remaining_time":1.490914286},
{"learn":[4.571019224],"iteration":267,"passed_time":0.5446520023,"remaining_time":1.487631588},
{"learn":[4.565766631],"iteration":268,"passed_time":0.5460705765,"remaining_time":1.483931567},
{"learn":[4.563383471],"iteration":269,"passed_time":0.5475974805,"remaining_time":1.480541336},
{"learn":[4.558165805],"iteration":270,"passed_time":0.5491722947,"remaining_time":1.477293737},
{"learn":[4.55629209],"iteration":271,"passed_time":0.5509606243,"remaining_time":1.474629906},
{"learn":[4.549383848],"iteration":272,"passed_time":0.5535116088,"remaining_time":1.474003442},
{"learn":[4.546227503],"iteration":273,"passed_time":0.5550507524,"remaining_time":1.470681921},
{"learn":[4.540620977],"iteration":274,"passed_time":0.556618341,"remaining_time":1.467448354},
{"learn":[4.532898237],"iteration":275,"passed_time":0.5579394286,"remaining_time":1.46358024},
{"learn":[4.529757367],"iteration":276,"passed_time":0.5599183872,"remaining_time":1.461447631},
{"learn":[4.52579294],"iteration":277,"passed_time":0.56173496,"remaining_time":1.458894392},
{"learn":[4.521572155],"iteration":278,"passed_time":0.5634927416,"remaining_time":1.456194504},
{"learn":[4.518818099],"iteration":279,"passed_time":0.5649482242,"remaining_time":1.452724005},
{"learn":[4.514012334],"iteration":280,"passed_time":0.5666796311,"remaining_time":1.44997386},
{"learn":[4.508331416],"iteration":281,"passed_time":0.5695662878,"remaining_time":1.450172321},
{"learn":[4.506038537],"iteration":282,"passed_time":0.5712586524,"remaining_time":1.447323158},
{"learn":[4.505805643],"iteration":283,"passed_time":0.5730099009,"remaining_time":1.444630595},
{"learn":[4.501550352],"iteration":284,"passed_time":0.5748261643,"remaining_time":1.442107745},
{"learn":[4.494692643],"iteration":285,"passed_time":0.5767645024,"remaining_time":1.439894597},
{"learn":[4.489330245],"iteration":286,"passed_time":0.5792161596,"remaining_time":1.438958613},
{"learn":[4.484826955],"iteration":287,"passed_time":0.5811126427,"remaining_time":1.436639589},
{"learn":[4.478285428],"iteration":288,"passed_time":0.5834078919,"remaining_time":1.435304537},
{"learn":[4.475311671],"iteration":289,"passed_time":0.5847959672,"remaining_time":1.431741851},
{"learn":[4.471581298],"iteration":290,"passed_time":0.5864359754,"remaining_time":1.428807926},
{"learn":[4.469164956],"iteration":291,"passed_time":0.587910692,"remaining_time":1.425482089},
{"learn":[4.462068024],"iteration":292,"passed_time":0.5893501727,"remaining_time":1.422083864},
{"learn":[4.458540976],"iteration":293,"passed_time":0.5910513694,"remaining_time":1.419327438},
{"learn":[4.455757458],"iteration":294,"passed_time":0.5926028449,"remaining_time":1.416220358},
{"learn":[4.453027414],"iteration":295,"passed_time":0.5942773807,"remaining_time":1.413416473},
{"learn":[4.450659338],"iteration":296,"passed_time":0.5959167895,"remaining_time":1.410537047},
{"learn":[4.444696901],"iteration":297,"passed_time":0.5984487264,"remaining_time":1.409768476},
{"learn":[4.442052813],"iteration":298,"passed_time":0.60028124,"remaining_time":1.407348325},
{"learn":[4.440036756],"iteration":299,"passed_time":0.601660717,"remaining_time":1.403875006},
{"learn":[4.435017051],"iteration":300,"passed_time":0.6031695547,"remaining_time":1.400716009},
{"learn":[4.429962125],"iteration":301,"passed_time":0.6046400173,"remaining_time":1.397479245},
{"learn":[4.427666256],"iteration":302,"passed_time":0.606039667,"remaining_time":1.394091247},
{"learn":[4.425030004],"iteration":303,"passed_time":0.6074553407,"remaining_time":1.390753017},
{"learn":[4.422588771],"iteration":304,"passed_time":0.6088797491,"remaining_time":1.387447297},
{"learn":[4.418936667],"iteration":305,"passed_time":0.6105960996,"remaining_time":1.384815991},
{"learn":[4.416887976],"iteration":306,"passed_time":0.6127803085,"remaining_time":1.383246755},
{"learn":[4.413773354],"iteration":307,"passed_time":0.6154009944,"remaining_time":1.382654182},
{"learn":[4.411129391],"iteration":308,"passed_time":0.6168411086,"remaining_time":1.379408434},
{"learn":[4.40850819],"iteration":309,"passed_time":0.6182684886,"remaining_time":1.376145991},
{"learn":[4.404880292],"iteration":310,"passed_time":0.6198501424,"remaining_time":1.373237132},
{"learn":[4.404593827],"iteration":311,"passed_time":0.621184341,"remaining_time":1.369791111},
{"learn":[4.402139942],"iteration":312,"passed_time":0.6228145613,"remaining_time":1.367008318},
{"learn":[4.400284725],"iteration":313,"passed_time":0.6242969099,"remaining_time":1.36390981},
{"learn":[4.395805521],"iteration":314,"passed_time":0.6258459318,"remaining_time":1.36096655},
{"learn":[4.392838833],"iteration":315,"passed_time":0.6300791867,"remaining_time":1.36384229},
{"learn":[4.389213061],"iteration":316,"passed_time":0.6327128181,"remaining_time":1.363226671},
{"learn":[4.3861981],"iteration":317,"passed_time":0.6344926626,"remaining_time":1.360767283},
{"learn":[4.385054234],"iteration":318,"passed_time":0.6363424326,"remaining_time":1.358461431},
{"learn":[4.379364607],"iteration":319,"passed_time":0.6384600328,"remaining_time":1.35672757},
{"learn":[4.378387619],"iteration":320,"passed_time":0.6399345614,"remaining_time":1.35363105},
{"learn":[4.375816727],"iteration":321,"passed_time":0.6413731395,"remaining_time":1.350468909},
{"learn":[4.374600202],"iteration":322,"passed_time":0.64329662,"remaining_time":1.348333782},
{"learn":[4.37098897],"iteration":323,"passed_time":0.6461640731,"remaining_time":1.348169486},
{"learn":[4.367418484],"iteration":324,"passed_time":0.6476925894,"remaining_time":1.345207686},
{"learn":[4.363584638],"iteration":325,"passed_time":0.6491379471,"remaining_time":1.34208275},
{"learn":[4.360770706],"iteration":326,"passed_time":0.6513819543,"remaining_time":1.34061179},
{"learn":[4.358675808],"iteration":327,"passed_time":0.6530175559,"remaining_time":1.337889627},
{"learn":[4.354228195],"iteration":328,"passed_time":0.6545905815,"remaining_time":1.335046444},
{"learn":[4.353773425],"iteration":329,"passed_time":0.655875912,"remaining_time":1.331626852},
{"learn":[4.351648009],"iteration":330,"passed_time":0.6573644825,"remaining_time":1.328630933},
{"learn":[4.348209927],"iteration":331,"passed_time":0.6595305864,"remaining_time":1.327007324},
{"learn":[4.345852733],"iteration":332,"passed_time":0.6611225136,"remaining_time":1.32423038},
{"learn":[4.34237339],"iteration":333,"passed_time":0.6627054352,"remaining_time":1.321442574},
{"learn":[4.340814362],"iteration":334,"passed_time":0.6662558874,"remaining_time":1.322567657},
{"learn":[4.339707068],"iteration":335,"passed_time":0.6690677372,"remaining_time":1.32220529},
{"learn":[4.335430786],"iteration":336,"passed_time":0.6722561075,"remaining_time":1.322569137},
{"learn":[4.33521887],"iteration":337,"passed_time":0.6760723445,"remaining_time":1.324141693},
{"learn":[4.328507238],"iteration":338,"passed_time":0.6803989108,"remaining_time":1.326677522},
{"learn":[4.326140732],"iteration":339,"passed_time":0.6821368873,"remaining_time":1.324148075},
{"learn":[4.323785636],"iteration":340,"passed_time":0.6837308693,"remaining_time":1.321344994},
{"learn":[4.320632534],"iteration":341,"passed_time":0.6852536986,"remaining_time":1.318412087},
{"learn":[4.31973724],"iteration":342,"passed_time":0.6867428286,"remaining_time":1.315422852},
{"learn":[4.318000924],"iteration":343,"passed_time":0.6907966568,"remaining_time":1.317333159},
{"learn":[4.312713628],"iteration":344,"passed_time":0.6936384343,"remaining_time":1.316907752},
{"learn":[4.308220789],"iteration":345,"passed_time":0.6956945159,"remaining_time":1.314983276},
{"learn":[4.305890947],"iteration":346,"passed_time":0.6977310898,"remaining_time":1.31302133},
{"learn":[4.305137856],"iteration":347,"passed_time":0.6998176312,"remaining_time":1.311152573},
{"learn":[4.304787172],"iteration":348,"passed_time":0.7017052552,"remaining_time":1.308911522},
{"learn":[4.30350134],"iteration":349,"passed_time":0.7038364244,"remaining_time":1.307124788},
{"learn":[4.30293809],"iteration":350,"passed_time":0.7063657773,"remaining_time":1.306072335},
{"learn":[4.299548459],"iteration":351,"passed_time":0.7096122168,"remaining_time":1.306331581},
{"learn":[4.294768408],"iteration":352,"passed_time":0.7118869459,"remaining_time":1.304789955},
{"learn":[4.294581479],"iteration":353,"passed_time":0.7139494798,"remaining_time":1.30285696},
{"learn":[4.292551604],"iteration":354,"passed_time":0.7163109842,"remaining_time":1.301466436},
{"learn":[4.288628894],"iteration":355,"passed_time":0.7208962906,"remaining_time":1.30409329},
{"learn":[4.287802767],"iteration":356,"passed_time":0.7269795901,"remaining_time":1.309377805},
{"learn":[4.284566905],"iteration":357,"passed_time":0.730859461,"remaining_time":1.310647413},
{"learn":[4.27890232],"iteration":358,"passed_time":0.7341031077,"remaining_time":1.310752346},
{"learn":[4.276938023],"iteration":359,"passed_time":0.7369726464,"remaining_time":1.310173594},
{"learn":[4.273425094],"iteration":360,"passed_time":0.7479131331,"remaining_time":1.323868399},
{"learn":[4.269726505],"iteration":361,"passed_time":0.7514197012,"remaining_time":1.32432533},
{"learn":[4.265565857],"iteration":362,"passed_time":0.7561762907,"remaining_time":1.326953987},
{"learn":[4.262117173],"iteration":363,"passed_time":0.7610226716,"remaining_time":1.329698954},
{"learn":[4.259185148],"iteration":364,"passed_time":0.7629467557,"remaining_time":1.327318328},
{"learn":[4.257668507],"iteration":365,"passed_time":0.7677278988,"remaining_time":1.329889311},
{"learn":[4.253432436],"iteration":366,"passed_time":0.7733042069,"remaining_time":1.333791725},
{"learn":[4.250216667],"iteration":367,"passed_time":0.7756889833,"remaining_time":1.332161515},
{"learn":[4.24514828],"iteration":368,"passed_time":0.77826121,"remaining_time":1.33084776},
{"learn":[4.244015772],"iteration":369,"passed_time":0.7819935797,"remaining_time":1.331502582},
{"learn":[4.240329192],"iteration":370,"passed_time":0.7871477964,"remaining_time":1.334544377},
{"learn":[4.236718014],"iteration":371,"passed_time":0.7930077752,"remaining_time":1.338733556},
{"learn":[4.233495944],"iteration":372,"passed_time":0.8013021701,"remaining_time":1.34696102},
{"learn":[4.230357491],"iteration":373,"passed_time":0.8053151378,"remaining_time":1.347933894},
{"learn":[4.227381215],"iteration":374,"passed_time":0.8081761098,"remaining_time":1.346960183},
{"learn":[4.226169067],"iteration":375,"passed_time":0.8183058926,"remaining_time":1.358039566},
{"learn":[4.225963861],"iteration":376,"passed_time":0.8210316746,"remaining_time":1.356771176},
{"learn":[4.224346548],"iteration":377,"passed_time":0.8230042936,"remaining_time":1.354255742},
{"learn":[4.222595381],"iteration":378,"passed_time":0.8282986868,"remaining_time":1.357185975},
{"learn":[4.219700938],"iteration":379,"passed_time":0.8323942073,"remaining_time":1.358116865},
{"learn":[4.216356207],"iteration":380,"passed_time":0.8354183263,"remaining_time":1.357280693},
{"learn":[4.214326494],"iteration":381,"passed_time":0.8382027594,"remaining_time":1.356045302},
{"learn":[4.212901398],"iteration":382,"passed_time":0.8478543093,"remaining_time":1.365864514},
{"learn":[4.211331091],"iteration":383,"passed_time":0.8514483286,"remaining_time":1.365865027},
{"learn":[4.208624791],"iteration":384,"passed_time":0.8539228215,"remaining_time":1.364058533},
{"learn":[4.204659106],"iteration":385,"passed_time":0.8563801424,"remaining_time":1.362221263},
{"learn":[4.202968852],"iteration":386,"passed_time":0.8592260567,"remaining_time":1.360996312},
{"learn":[4.197261935],"iteration":387,"passed_time":0.8627018056,"remaining_time":1.360756456},
{"learn":[4.196934403],"iteration":388,"passed_time":0.8650346758,"remaining_time":1.358704851},
{"learn":[4.192479929],"iteration":389,"passed_time":0.8667135063,"remaining_time":1.355628818},
{"learn":[4.190243116],"iteration":390,"passed_time":0.8685977399,"remaining_time":1.352879856},
{"learn":[4.185852431],"iteration":391,"passed_time":0.8714101636,"remaining_time":1.351574948},
{"learn":[4.180967944],"iteration":392,"passed_time":0.8743797954,"remaining_time":1.35050518},
{"learn":[4.178283162],"iteration":393,"passed_time":0.8771498899,"remaining_time":1.349118866},
{"learn":[4.176341157],"iteration":394,"passed_time":0.8791363911,"remaining_time":1.346525359},
{"learn":[4.176041504],"iteration":395,"passed_time":0.8805732276,"remaining_time":1.343096539},
{"learn":[4.175564513],"iteration":396,"passed_time":0.8819181408,"remaining_time":1.339538133},
{"learn":[4.170830274],"iteration":397,"passed_time":0.883344852,"remaining_time":1.336114575},
{"learn":[4.167804808],"iteration":398,"passed_time":0.8849335214,"remaining_time":1.332944978},
{"learn":[4.165860548],"iteration":399,"passed_time":0.888738525,"remaining_time":1.333107788},
{"learn":[4.160950571],"iteration":400,"passed_time":0.8905363809,"remaining_time":1.330252599},
{"learn":[4.158544115],"iteration":401,"passed_time":0.8924474214,"remaining_time":1.32757104},
{"learn":[4.154448767],"iteration":402,"passed_time":0.8940051987,"remaining_time":1.324369984},
{"learn":[4.15197457],"iteration":403,"passed_time":0.8954676578,"remaining_time":1.321036446},
{"learn":[4.149562679],"iteration":404,"passed_time":0.897085426,"remaining_time":1.317940317},
{"learn":[4.149327961],"iteration":405,"passed_time":0.8987864284,"remaining_time":1.314973247},
{"learn":[4.147444889],"iteration":406,"passed_time":0.9002269802,"remaining_time":1.311632922},
{"learn":[4.147254809],"iteration":407,"passed_time":0.9030513411,"remaining_time":1.310309789},
{"learn":[4.144589165],"iteration":408,"passed_time":0.9056656133,"remaining_time":1.30867574},
{"learn":[4.141691034],"iteration":409,"passed_time":0.9081545983,"remaining_time":1.306856617},
{"learn":[4.138893468],"iteration":410,"passed_time":0.909939859,"remaining_time":1.304025735},
{"learn":[4.136964597],"iteration":411,"passed_time":0.9120001796,"remaining_time":1.301592489},
{"learn":[4.133773523],"iteration":412,"passed_time":0.9145754718,"remaining_time":1.299892983},
{"learn":[4.131363444],"iteration":413,"passed_time":0.9187188044,"remaining_time":1.300408742},
{"learn":[4.130228592],"iteration":414,"passed_time":0.9207552094,"remaining_time":1.297932042},
{"learn":[4.12884186],"iteration":415,"passed_time":0.9229779961,"remaining_time":1.29571911},
{"learn":[4.12413494],"iteration":416,"passed_time":0.9249439006,"remaining_time":1.293146988},
{"learn":[4.119422508],"iteration":417,"passed_time":0.9272217324,"remaining_time":1.291012077},
{"learn":[4.117038244],"iteration":418,"passed_time":0.9291742697,"remaining_time":1.288425419},
{"learn":[4.116067631],"iteration":419,"passed_time":0.9312844276,"remaining_time":1.286059448},
{"learn":[4.110343455],"iteration":420,"passed_time":0.9351215308,"remaining_time":1.286069754},
{"learn":[4.105604544],"iteration":421,"passed_time":0.936876253,"remaining_time":1.283209655},
{"learn":[4.103390131],"iteration":422,"passed_time":0.9386231386,"remaining_time":1.280344092},
{"learn":[4.096724402],"iteration":423,"passed_time":0.9402665772,"remaining_time":1.277343275},
{"learn":[4.093431279],"iteration":424,"passed_time":0.9416884541,"remaining_time":1.274049085},
{"learn":[4.091412744],"iteration":425,"passed_time":0.9432583629,"remaining_time":1.270963146},
{"learn":[4.091192901],"iteration":426,"passed_time":0.9447236102,"remaining_time":1.267743861},
{"learn":[4.088994581],"iteration":427,"passed_time":0.9464621936,"remaining_time":1.264898072},
{"learn":[4.087845355],"iteration":428,"passed_time":0.9497692391,"remaining_time":1.264145071},
{"learn":[4.083650279],"iteration":429,"passed_time":0.9516681173,"remaining_time":1.261513551},
{"learn":[4.079840652],"iteration":430,"passed_time":0.9534512421,"remaining_time":1.258732614},
{"learn":[4.075707828],"iteration":431,"passed_time":0.9549847786,"remaining_time":1.255628135},
{"learn":[4.071345409],"iteration":432,"passed_time":0.9563152323,"remaining_time":1.252264981},
{"learn":[4.067460475],"iteration":433,"passed_time":0.9577406636,"remaining_time":1.249035059},
{"learn":[4.064914749],"iteration":434,"passed_time":0.9593156687,"remaining_time":1.246007708},
{"learn":[4.063823175],"iteration":435,"passed_time":0.960790077,"remaining_time":1.242856889},
{"learn":[4.058898471],"iteration":436,"passed_time":0.963828911,"remaining_time":1.241729238},
{"learn":[4.054120355],"iteration":437,"passed_time":0.9655919491,"remaining_time":1.23895588},
{"learn":[4.052715901],"iteration":438,"passed_time":0.9681675184,"remaining_time":1.237225462},
{"learn":[4.052114167],"iteration":439,"passed_time":0.9697252025,"remaining_time":1.234195712},
{"learn":[4.051377267],"iteration":440,"passed_time":0.9713795393,"remaining_time":1.231295153},
{"learn":[4.049275336],"iteration":441,"passed_time":0.9729338896,"remaining_time":1.228274005},
{"learn":[4.047099198],"iteration":442,"passed_time":0.9743649234,"remaining_time":1.22510443},
{"learn":[4.044348685],"iteration":443,"passed_time":0.9757331628,"remaining_time":1.221864051},
{"learn":[4.042822379],"iteration":444,"passed_time":0.9772530064,"remaining_time":1.218821165},
{"learn":[4.041258611],"iteration":445,"passed_time":0.9802360794,"remaining_time":1.217602664},
{"learn":[4.040044254],"iteration":446,"passed_time":0.9829982994,"remaining_time":1.216103042},
{"learn":[4.036860137],"iteration":447,"passed_time":0.9849124105,"remaining_time":1.213552791},
{"learn":[4.036372284],"iteration":448,"passed_time":0.9866107906,"remaining_time":1.210740636},
{"learn":[4.03368231],"iteration":449,"passed_time":0.9882193162,"remaining_time":1.207823609},
{"learn":[4.032439519],"iteration":450,"passed_time":0.9898844172,"remaining_time":1.204981253},
{"learn":[4.032008634],"iteration":451,"passed_time":0.9912188117,"remaining_time":1.201743161},
{"learn":[4.030034932],"iteration":452,"passed_time":0.9932445553,"remaining_time":1.199348282},
{"learn":[4.028173412],"iteration":453,"passed_time":0.9958038814,"remaining_time":1.197596738},
{"learn":[4.023806097],"iteration":454,"passed_time":0.9984240922,"remaining_time":1.195914572},
{"learn":[4.020239186],"iteration":455,"passed_time":0.9999030907,"remaining_time":1.192866845},
{"learn":[4.017384838],"iteration":456,"passed_time":1.001231033,"remaining_time":1.189646501},
{"learn":[4.016468229],"iteration":457,"passed_time":1.002554908,"remaining_time":1.186429607},
{"learn":[4.014530169],"iteration":458,"passed_time":1.004069256,"remaining_time":1.183445464},
{"learn":[4.012884822],"iteration":459,"passed_time":1.005916382,"remaining_time":1.180858361},
{"learn":[4.008924707],"iteration":460,"passed_time":1.007261465,"remaining_time":1.177687483},
{"learn":[4.008286778],"iteration":461,"passed_time":1.010265403,"remaining_time":1.176456248},
{"learn":[4.006444202],"iteration":462,"passed_time":1.012468691,"remaining_time":1.174288741},
{"learn":[4.003284363],"iteration":463,"passed_time":1.014553942,"remaining_time":1.171984726},
{"learn":[3.999811484],"iteration":464,"passed_time":1.016119817,"remaining_time":1.16908409},
{"learn":[3.997483319],"iteration":465,"passed_time":1.017752784,"remaining_time":1.166266066},
{"learn":[3.99708333],"iteration":466,"passed_time":1.019200135,"remaining_time":1.163241268},
{"learn":[3.995860263],"iteration":467,"passed_time":1.020595693,"remaining_time":1.160164335},
{"learn":[3.994131111],"iteration":468,"passed_time":1.021846938,"remaining_time":1.156931181},
{"learn":[3.993125499],"iteration":469,"passed_time":1.023290024,"remaining_time":1.153922793},
{"learn":[3.992954084],"iteration":470,"passed_time":1.026482768,"remaining_time":1.152886167},
{"learn":[3.990635743],"iteration":471,"passed_time":1.02874205,"remaining_time":1.150796191},
{"learn":[3.986678254],"iteration":472,"passed_time":1.030349198,"remaining_time":1.147978916},
{"learn":[3.986393291],"iteration":473,"passed_time":1.032022422,"remaining_time":1.145240072},
{"learn":[3.986152671],"iteration":474,"passed_time":1.033693108,"remaining_time":1.142502909},
{"learn":[3.985596662],"iteration":475,"passed_time":1.035276449,"remaining_time":1.139674074},
{"learn":[3.983853457],"iteration":476,"passed_time":1.036691976,"remaining_time":1.136666465},
{"learn":[3.983263928],"iteration":477,"passed_time":1.039200779,"remaining_time":1.134859428},
{"learn":[3.980067202],"iteration":478,"passed_time":1.041168866,"remaining_time":1.132461334},
{"learn":[3.978115407],"iteration":479,"passed_time":1.043952954,"remaining_time":1.130949034},
{"learn":[3.972661644],"iteration":480,"passed_time":1.045644291,"remaining_time":1.128252363},
{"learn":[3.969938254],"iteration":481,"passed_time":1.047217433,"remaining_time":1.125432842},
{"learn":[3.968211434],"iteration":482,"passed_time":1.048753241,"remaining_time":1.122578521},
{"learn":[3.966113368],"iteration":483,"passed_time":1.050290149,"remaining_time":1.11973082},
{"learn":[3.962246044],"iteration":484,"passed_time":1.051764959,"remaining_time":1.116822585},
{"learn":[3.961319703],"iteration":485,"passed_time":1.054416339,"remaining_time":1.115164605},
{"learn":[3.96078191],"iteration":486,"passed_time":1.056530187,"remaining_time":1.112936316},
{"learn":[3.958913633],"iteration":487,"passed_time":1.058914101,"remaining_time":1.110991843},
{"learn":[3.957428286],"iteration":488,"passed_time":1.06054033,"remaining_time":1.108253801},
{"learn":[3.952641965],"iteration":489,"passed_time":1.062556316,"remaining_time":1.105925961},
{"learn":[3.951486786],"iteration":490,"passed_time":1.064062168,"remaining_time":1.103070557},
{"learn":[3.94938344],"iteration":491,"passed_time":1.065461639,"remaining_time":1.100110798},
{"learn":[3.947297924],"iteration":492,"passed_time":1.066935686,"remaining_time":1.097234063},
{"learn":[3.946284886],"iteration":493,"passed_time":1.068474249,"remaining_time":1.094429089},
{"learn":[3.943288204],"iteration":494,"passed_time":1.071254892,"remaining_time":1.092896405},
{"learn":[3.943076488],"iteration":495,"passed_time":1.073652764,"remaining_time":1.090969744},
{"learn":[3.942347078],"iteration":496,"passed_time":1.075145707,"remaining_time":1.088125333},
{"learn":[3.940251541],"iteration":497,"passed_time":1.076740327,"remaining_time":1.085388844},
{"learn":[3.939011019],"iteration":498,"passed_time":1.078213675,"remaining_time":1.082535172},
{"learn":[3.938760512],"iteration":499,"passed_time":1.07995232,"remaining_time":1.07995232},
{"learn":[3.934522727],"iteration":500,"passed_time":1.081658232,"remaining_time":1.077340235},
{"learn":[3.930091193],"iteration":501,"passed_time":1.083045961,"remaining_time":1.074416113},
{"learn":[3.927671752],"iteration":502,"passed_time":1.086192623,"remaining_time":1.073236051},
{"learn":[3.927280041],"iteration":503,"passed_time":1.088278493,"remaining_time":1.071004231},
{"learn":[3.925987561],"iteration":504,"passed_time":1.090696514,"remaining_time":1.069098563},
{"learn":[3.921645957],"iteration":505,"passed_time":1.092479357,"remaining_time":1.066570756},
{"learn":[3.920333743],"iteration":506,"passed_time":1.09385073,"remaining_time":1.063645779},
{"learn":[3.918659461],"iteration":507,"passed_time":1.09512991,"remaining_time":1.060637629},
{"learn":[3.916124385],"iteration":508,"passed_time":1.096550475,"remaining_time":1.057772659},
{"learn":[3.913849268],"iteration":509,"passed_time":1.098503327,"remaining_time":1.055424765},
{"learn":[3.912826119],"iteration":510,"passed_time":1.101165935,"remaining_time":1.053757617},
{"learn":[3.910034145],"iteration":511,"passed_time":1.103062645,"remaining_time":1.051356583},
{"learn":[3.90792379],"iteration":512,"passed_time":1.104880924,"remaining_time":1.04888306},
{"learn":[3.907823851],"iteration":513,"passed_time":1.106349818,"remaining_time":1.046081735},
{"learn":[3.904527401],"iteration":514,"passed_time":1.10797588,"remaining_time":1.043433596},
{"learn":[3.903378283],"iteration":515,"passed_time":1.10934619,"remaining_time":1.040549527},
{"learn":[3.902170135],"iteration":516,"passed_time":1.110668548,"remaining_time":1.037626516},
{"learn":[3.899435429],"iteration":517,"passed_time":1.111984849,"remaining_time":1.034704048},
{"learn":[3.897497505],"iteration":518,"passed_time":1.115064854,"remaining_time":1.03342234},
{"learn":[3.896426119],"iteration":519,"passed_time":1.117722736,"remaining_time":1.031744064},
{"learn":[3.896044669],"iteration":520,"passed_time":1.120103871,"remaining_time":1.029807589},
{"learn":[3.892795942],"iteration":521,"passed_time":1.122548013,"remaining_time":1.027927107},
{"learn":[3.892413888],"iteration":522,"passed_time":1.124585273,"remaining_time":1.025673375},
{"learn":[3.891738985],"iteration":523,"passed_time":1.12632491,"remaining_time":1.02315011},
{"learn":[3.88822057],"iteration":524,"passed_time":1.128070674,"remaining_time":1.020635372},
{"learn":[3.883837053],"iteration":525,"passed_time":1.131239145,"remaining_time":1.019405617},
{"learn":[3.881769742],"iteration":526,"passed_time":1.133591532,"remaining_time":1.017436043},
{"learn":[3.880356898],"iteration":527,"passed_time":1.135628492,"remaining_time":1.015183045},
{"learn":[3.879250273],"iteration":528,"passed_time":1.137791187,"remaining_time":1.013042815},
{"learn":[3.877174493],"iteration":529,"passed_time":1.14052729,"remaining_time":1.011410993},
{"learn":[3.875854201],"iteration":530,"passed_time":1.142862419,"remaining_time":1.009420856},
{"learn":[3.873189396],"iteration":531,"passed_time":1.14648443,"remaining_time":1.008561491},
{"learn":[3.871583368],"iteration":532,"passed_time":1.148542333,"remaining_time":1.006321331},
{"learn":[3.869622679],"iteration":533,"passed_time":1.151208179,"remaining_time":1.004612381},
{"learn":[3.866860164],"iteration":534,"passed_time":1.152971906,"remaining_time":1.002115768},
{"learn":[3.864498444],"iteration":535,"passed_time":1.154390015,"remaining_time":0.9993226998},
{"learn":[3.861416322],"iteration":536,"passed_time":1.155861346,"remaining_time":0.996580639},
{"learn":[3.860265769],"iteration":537,"passed_time":1.157346763,"remaining_time":0.9938553984},
{"learn":[3.859328725],"iteration":538,"passed_time":1.159262193,"remaining_time":0.9915025433},
{"learn":[3.858521278],"iteration":539,"passed_time":1.162216904,"remaining_time":0.9900366215},
{"learn":[3.85599111],"iteration":540,"passed_time":1.164529759,"remaining_time":0.9880206277},
{"learn":[3.852379816],"iteration":541,"passed_time":1.166198677,"remaining_time":0.9854593985},
{"learn":[3.851327537],"iteration":542,"passed_time":1.167836889,"remaining_time":0.9828756134},
{"learn":[3.847854898],"iteration":543,"passed_time":1.169278704,"remaining_time":0.980130678},
{"learn":[3.847083414],"iteration":544,"passed_time":1.170768404,"remaining_time":0.9774305023},
{"learn":[3.845397429],"iteration":545,"passed_time":1.172299335,"remaining_time":0.9747690443},
{"learn":[3.841933528],"iteration":546,"passed_time":1.173973725,"remaining_time":0.9722305251},
{"learn":[3.840996474],"iteration":547,"passed_time":1.176470873,"remaining_time":0.9703737855},
{"learn":[3.838355966],"iteration":548,"passed_time":1.178489468,"remaining_time":0.9681215845},
{"learn":[3.83342799],"iteration":549,"passed_time":1.180531925,"remaining_time":0.965889757},
{"learn":[3.828161535],"iteration":550,"passed_time":1.182273208,"remaining_time":0.9634131948},
{"learn":[3.823502399],"iteration":551,"passed_time":1.184233278,"remaining_time":0.9611168634},
{"learn":[3.820068862],"iteration":552,"passed_time":1.185963849,"remaining_time":0.9586362393},
{"learn":[3.817951642],"iteration":553,"passed_time":1.18742419,"remaining_time":0.9559407743},
{"learn":[3.815785958],"iteration":554,"passed_time":1.191406617,"remaining_time":0.9552719724},
{"learn":[3.81503012],"iteration":555,"passed_time":1.193104501,"remaining_time":0.9527669035},
{"learn":[3.813529315],"iteration":556,"passed_time":1.195526461,"remaining_time":0.9508406141},
{"learn":[3.808881326],"iteration":557,"passed_time":1.197173684,"remaining_time":0.9482988683},
{"learn":[3.808740434],"iteration":558,"passed_time":1.198771131,"remaining_time":0.9457210532},
{"learn":[3.80714352],"iteration":559,"passed_time":1.200358307,"remaining_time":0.9431386701},
{"learn":[3.80573346],"iteration":560,"passed_time":1.202163572,"remaining_time":0.9407304958},
{"learn":[3.803370052],"iteration":561,"passed_time":1.20393306,"remaining_time":0.9382965838},
{"learn":[3.803215211],"iteration":562,"passed_time":1.206818649,"remaining_time":0.9367313491},
{"learn":[3.801309667],"iteration":563,"passed_time":1.20868024,"remaining_time":0.9343698307},
{"learn":[3.800003847],"iteration":564,"passed_time":1.210286135,"remaining_time":0.9318132191},
{"learn":[3.798026138],"iteration":565,"passed_time":1.211949792,"remaining_time":0.9293042577},
{"learn":[3.794745847],"iteration":566,"passed_time":1.213536428,"remaining_time":0.9267394595},
{"learn":[3.794312041],"iteration":567,"passed_time":1.215117656,"remaining_time":0.9241739918},
{"learn":[3.792205926],"iteration":568,"passed_time":1.217064876,"remaining_time":0.9218892122},
{"learn":[3.788991061],"iteration":569,"passed_time":1.22008581,"remaining_time":0.920415611},
{"learn":[3.787391572],"iteration":570,"passed_time":1.222199505,"remaining_time":0.9182549697},
{"learn":[3.7826445],"iteration":571,"passed_time":1.226567493,"remaining_time":0.917781271},
{"learn":[3.781700331],"iteration":572,"passed_time":1.228507759,"remaining_time":0.9154848397},
{"learn":[3.780045374],"iteration":573,"passed_time":1.230482843,"remaining_time":0.9132154901},
{"learn":[3.775462644],"iteration":574,"passed_time":1.232078359,"remaining_time":0.9106666129},
{"learn":[3.773711943],"iteration":575,"passed_time":1.233455684,"remaining_time":0.9079604343},
{"learn":[3.772415806],"iteration":576,"passed_time":1.23592315,"remaining_time":0.9060580459},
{"learn":[3.770170875],"iteration":577,"passed_time":1.238337865,"remaining_time":0.9041151884},
{"learn":[3.765166479],"iteration":578,"passed_time":1.242056932,"remaining_time":0.9031191161},
{"learn":[3.763976102],"iteration":579,"passed_time":1.243935203,"remaining_time":0.9007806644},
{"learn":[3.760761708],"iteration":580,"passed_time":1.245951237,"remaining_time":0.8985431466},
{"learn":[3.758155662],"iteration":581,"passed_time":1.247780186,"remaining_time":0.8961720236},
{"learn":[3.756844548],"iteration":582,"passed_time":1.249348505,"remaining_time":0.8936163403},
{"learn":[3.753098923],"iteration":583,"passed_time":1.253958777,"remaining_time":0.8932309098},
{"learn":[3.751618946],"iteration":584,"passed_time":1.256017215,"remaining_time":0.8910207594},
{"learn":[3.751398464],"iteration":585,"passed_time":1.258298341,"remaining_time":0.8889684524},
{"learn":[3.749920103],"iteration":586,"passed_time":1.259734135,"remaining_time":0.8863206097},
{"learn":[3.748237465],"iteration":587,"passed_time":1.261289812,"remaining_time":0.8837608884},
{"learn":[3.746021536],"iteration":588,"passed_time":1.262798021,"remaining_time":0.8811714542},
{"learn":[3.74417648],"iteration":589,"passed_time":1.264583528,"remaining_time":0.878778384},
{"learn":[3.738788389],"iteration":590,"passed_time":1.267776578,"remaining_time":0.8773614559},
{"learn":[3.736021611],"iteration":591,"passed_time":1.269672661,"remaining_time":0.8750446721},
{"learn":[3.734546151],"iteration":592,"passed_time":1.272174527,"remaining_time":0.8731450798},
{"learn":[3.733527479],"iteration":593,"passed_time":1.274033369,"remaining_time":0.8708039523},
{"learn":[3.733026392],"iteration":594,"passed_time":1.275607563,"remaining_time":0.8682706942},
{"learn":[3.730314752],"iteration":595,"passed_time":1.277506169,"remaining_time":0.8659605574},
{"learn":[3.727342596],"iteration":596,"passed_time":1.279266921,"remaining_time":0.8635587422},
{"learn":[3.725459604],"iteration":597,"passed_time":1.284011384,"remaining_time":0.8631648436},
{"learn":[3.723158842],"iteration":598,"passed_time":1.287004692,"remaining_time":0.8615841096},
{"learn":[3.722362756],"iteration":599,"passed_time":1.289258191,"remaining_time":0.8595054609},
{"learn":[3.721443615],"iteration":600,"passed_time":1.291456887,"remaining_time":0.857389847},
{"learn":[3.720743486],"iteration":601,"passed_time":1.293254003,"remaining_time":0.8550084606},
{"learn":[3.720215334],"iteration":602,"passed_time":1.295407866,"remaining_time":0.8528638849},
{"learn":[3.719436563],"iteration":603,"passed_time":1.298243891,"remaining_time":0.8511665244},
{"learn":[3.715046574],"iteration":604,"passed_time":1.30005035,"remaining_time":0.848793204},
{"learn":[3.71443396],"iteration":605,"passed_time":1.302792684,"remaining_time":0.8470302271},
{"learn":[3.712938941],"iteration":606,"passed_time":1.304503195,"remaining_time":0.8445959728},
{"learn":[3.712814764],"iteration":607,"passed_time":1.306374155,"remaining_time":0.8422675476},
{"learn":[3.71235348],"iteration":608,"passed_time":1.308679825,"remaining_time":0.8402197236},
{"learn":[3.711223749],"iteration":609,"passed_time":1.310365617,"remaining_time":0.8377747386},
{"learn":[3.710755648],"iteration":610,"passed_time":1.313355769,"remaining_time":0.8361626748},
{"learn":[3.708668039],"iteration":611,"passed_time":1.315950163,"remaining_time":0.8342952013},
{"learn":[3.705623591],"iteration":612,"passed_time":1.31958312,"remaining_time":0.8330810234},
{"learn":[3.704045802],"iteration":613,"passed_time":1.3216106,"remaining_time":0.8308496603},
{"learn":[3.699915209],"iteration":614,"passed_time":1.324797448,"remaining_time":0.8293447438},
{"learn":[3.696182221],"iteration":615,"passed_time":1.328349317,"remaining_time":0.8280619121},
{"learn":[3.694263278],"iteration":616,"passed_time":1.330286982,"remaining_time":0.8257697146},
{"learn":[3.693810229],"iteration":617,"passed_time":1.332443277,"remaining_time":0.8236138054},
{"learn":[3.690900932],"iteration":618,"passed_time":1.334785715,"remaining_time":0.8215724674},
{"learn":[3.688020895],"iteration":619,"passed_time":1.336309243,"remaining_time":0.8190282457},
{"learn":[3.685491894],"iteration":620,"passed_time":1.337898004,"remaining_time":0.8165271231},
{"learn":[3.684328128],"iteration":621,"passed_time":1.340414156,"remaining_time":0.8145925258},
{"learn":[3.680640153],"iteration":622,"passed_time":1.34350826,"remaining_time":0.813005801},
{"learn":[3.678932783],"iteration":623,"passed_time":1.345806344,"remaining_time":0.8109345918},
{"learn":[3.674167041],"iteration":624,"passed_time":1.348481252,"remaining_time":0.8090887512},
{"learn":[3.672200976],"iteration":625,"passed_time":1.350025268,"remaining_time":0.8065646171},
{"learn":[3.670606604],"iteration":626,"passed_time":1.35201412,"remaining_time":0.8043082407},
{"learn":[3.665506042],"iteration":627,"passed_time":1.35386156,"remaining_time":0.8019689495},
{"learn":[3.664214007],"iteration":628,"passed_time":1.355569078,"remaining_time":0.7995486932},
{"learn":[3.66261643],"iteration":629,"passed_time":1.357734186,"remaining_time":0.7973994426},
{"learn":[3.662118449],"iteration":630,"passed_time":1.359937477,"remaining_time":0.7952724705},
{"learn":[3.660871366],"iteration":631,"passed_time":1.362911546,"remaining_time":0.7935940646},
{"learn":[3.656695243],"iteration":632,"passed_time":1.364605533,"remaining_time":0.7911694007},
{"learn":[3.654497801],"iteration":633,"passed_time":1.366000296,"remaining_time":0.7885743032},
{"learn":[3.654189134],"iteration":634,"passed_time":1.367824086,"remaining_time":0.7862295926},
{"learn":[3.653957699],"iteration":635,"passed_time":1.369493604,"remaining_time":0.7837982261},
{"learn":[3.651920725],"iteration":636,"passed_time":1.371695086,"remaining_time":0.7816723959},
{"learn":[3.65106705],"iteration":637,"passed_time":1.375173901,"remaining_time":0.7802710848},
{"learn":[3.650612844],"iteration":638,"passed_time":1.377328788,"remaining_time":0.7781153247},
{"learn":[3.649884732],"iteration":639,"passed_time":1.379339339,"remaining_time":0.7758783782},
{"learn":[3.646276182],"iteration":640,"passed_time":1.381311617,"remaining_time":0.773620703},
{"learn":[3.645808194],"iteration":641,"passed_time":1.382962752,"remaining_time":0.7711848369},
{"learn":[3.645042989],"iteration":642,"passed_time":1.38429368,"remaining_time":0.7685736295},
{"learn":[3.639864499],"iteration":643,"passed_time":1.385720043,"remaining_time":0.7660191542},
{"learn":[3.637318478],"iteration":644,"passed_time":1.387116921,"remaining_time":0.7634519487},
{"learn":[3.636344905],"iteration":645,"passed_time":1.390727354,"remaining_time":0.7621013673},
{"learn":[3.634754643],"iteration":646,"passed_time":1.393433397,"remaining_time":0.7602503696},
{"learn":[3.630724975],"iteration":647,"passed_time":1.395261564,"remaining_time":0.7579198619},
{"learn":[3.629408252],"iteration":648,"passed_time":1.396941076,"remaining_time":0.7555105048},
{"learn":[3.62790646],"iteration":649,"passed_time":1.39852909,"remaining_time":0.7530541251},
{"learn":[3.627388973],"iteration":650,"passed_time":1.400087491,"remaining_time":0.7505845381},
{"learn":[3.625163557],"iteration":651,"passed_time":1.401599846,"remaining_time":0.7480931695},
{"learn":[3.623701985],"iteration":652,"passed_time":1.403716975,"remaining_time":0.7459261721},
{"learn":[3.622342639],"iteration":653,"passed_time":1.406453684,"remaining_time":0.7440871173},
{"learn":[3.621130639],"iteration":654,"passed_time":1.409427757,"remaining_time":0.7423703451},
{"learn":[3.619125665],"iteration":655,"passed_time":1.411543148,"remaining_time":0.7401994559},
{"learn":[3.618878783],"iteration":656,"passed_time":1.413140003,"remaining_time":0.7377580229},
{"learn":[3.616207429],"iteration":657,"passed_time":1.41450774,"remaining_time":0.7352000718},
{"learn":[3.61206486],"iteration":658,"passed_time":1.416302532,"remaining_time":0.7328667121},
{"learn":[3.611955873],"iteration":659,"passed_time":1.419399182,"remaining_time":0.7312056393},
{"learn":[3.610713743],"iteration":660,"passed_time":1.421516514,"remaining_time":0.7290379703},
{"learn":[3.610044025],"iteration":661,"passed_time":1.423954432,"remaining_time":0.7270341358},
{"learn":[3.607342669],"iteration":662,"passed_time":1.425887555,"remaining_time":0.7247724075},
{"learn":[3.602510618],"iteration":663,"passed_time":1.427585637,"remaining_time":0.7223927321},
{"learn":[3.600492392],"iteration":664,"passed_time":1.42905892,"remaining_time":0.719901862},
{"learn":[3.597171065],"iteration":665,"passed_time":1.431192507,"remaining_time":0.7177451913},
{"learn":[3.594358798],"iteration":666,"passed_time":1.432697767,"remaining_time":0.7152748973},
{"learn":[3.593945251],"iteration":667,"passed_time":1.435995935,"remaining_time":0.7136985787},
{"learn":[3.593607748],"iteration":668,"passed_time":1.438225883,"remaining_time":0.711588591},
{"learn":[3.592238714],"iteration":669,"passed_time":1.440494031,"remaining_time":0.7094970601},
{"learn":[3.590144654],"iteration":670,"passed_time":1.442451568,"remaining_time":0.7072527063},
{"learn":[3.587151536],"iteration":671,"passed_time":1.444176058,"remaining_time":0.7048954571},
{"learn":[3.586070865],"iteration":672,"passed_time":1.445916243,"remaining_time":0.7025477139},
{"learn":[3.585102746],"iteration":673,"passed_time":1.447549369,"remaining_time":0.7001499916},
{"learn":[3.584362847],"iteration":674,"passed_time":1.450782127,"remaining_time":0.6985247278},
{"learn":[3.581407561],"iteration":675,"passed_time":1.453072124,"remaining_time":0.6964428522},
{"learn":[3.57919422],"iteration":676,"passed_time":1.455597064,"remaining_time":0.6944724544},
{"learn":[3.577632204],"iteration":677,"passed_time":1.457320968,"remaining_time":0.6921199878},
{"learn":[3.573911195],"iteration":678,"passed_time":1.45881276,"remaining_time":0.6896596405},
{"learn":[3.573408216],"iteration":679,"passed_time":1.460071476,"remaining_time":0.6870924593},
{"learn":[3.571076482],"iteration":680,"passed_time":1.461477395,"remaining_time":0.6845980751},
{"learn":[3.568177107],"iteration":681,"passed_time":1.463593226,"remaining_time":0.6824378972},
{"learn":[3.564824621],"iteration":682,"passed_time":1.466246085,"remaining_time":0.6805270996},
{"learn":[3.562475026],"iteration":683,"passed_time":1.470237746,"remaining_time":0.6792326428},
{"learn":[3.561226889],"iteration":684,"passed_time":1.471964139,"remaining_time":0.6768886187},
{"learn":[3.559383467],"iteration":685,"passed_time":1.473633172,"remaining_time":0.6745201401},
{"learn":[3.555209766],"iteration":686,"passed_time":1.475171411,"remaining_time":0.6720941071},
{"learn":[3.55345383],"iteration":687,"passed_time":1.476708057,"remaining_time":0.6696699326},
{"learn":[3.552300968],"iteration":688,"passed_time":1.478205501,"remaining_time":0.6672306398},
{"learn":[3.551253986],"iteration":689,"passed_time":1.481198139,"remaining_time":0.6654658304},
{"learn":[3.549807725],"iteration":690,"passed_time":1.484230797,"remaining_time":0.6637153636},
{"learn":[3.547992926],"iteration":691,"passed_time":1.486111154,"remaining_time":0.6614483171},
{"learn":[3.545438607],"iteration":692,"passed_time":1.487707822,"remaining_time":0.6590567117},
{"learn":[3.543313763],"iteration":693,"passed_time":1.489248298,"remaining_time":0.6566426212},
{"learn":[3.542962896],"iteration":694,"passed_time":1.490895216,"remaining_time":0.6542777567},
{"learn":[3.539800465],"iteration":695,"passed_time":1.492264137,"remaining_time":0.651793531},
{"learn":[3.53953187],"iteration":696,"passed_time":1.496611808,"remaining_time":0.6506074289},
{"learn":[3.536332425],"iteration":697,"passed_time":1.499420816,"remaining_time":0.6487465423},
{"learn":[3.534993327],"iteration":698,"passed_time":1.501468713,"remaining_time":0.646555197},
{"learn":[3.531637011],"iteration":699,"passed_time":1.503123061,"remaining_time":0.6441955976},
{"learn":[3.531040284],"iteration":700,"passed_time":1.504574189,"remaining_time":0.6417513302},
{"learn":[3.529973872],"iteration":701,"passed_time":1.506017153,"remaining_time":0.6393064267},
{"learn":[3.527325183],"iteration":702,"passed_time":1.507447456,"remaining_time":0.6368590248},
{"learn":[3.527200815],"iteration":703,"passed_time":1.510021916,"remaining_time":0.6348955784},
{"learn":[3.523459911],"iteration":704,"passed_time":1.512365841,"remaining_time":0.6328339336},
{"learn":[3.522729934],"iteration":705,"passed_time":1.515099883,"remaining_time":0.6309339457},
{"learn":[3.522260582],"iteration":706,"passed_time":1.516996928,"remaining_time":0.6286847241},
{"learn":[3.518641591],"iteration":707,"passed_time":1.518701832,"remaining_time":0.6263572529},
{"learn":[3.516856405],"iteration":708,"passed_time":1.520052952,"remaining_time":0.6238863315},
{"learn":[3.515083413],"iteration":709,"passed_time":1.521383938,"remaining_time":0.621410341},
{"learn":[3.514671214],"iteration":710,"passed_time":1.522935646,"remaining_time":0.6190272878},
{"learn":[3.512617621],"iteration":711,"passed_time":1.52566564,"remaining_time":0.6171231802},
{"learn":[3.510747971],"iteration":712,"passed_time":1.52934232,"remaining_time":0.6155978202},
{"learn":[3.508149266],"iteration":713,"passed_time":1.531116615,"remaining_time":0.6133044142},
{"learn":[3.504557165],"iteration":714,"passed_time":1.532819932,"remaining_time":0.6109841686},
{"learn":[3.501367208],"iteration":715,"passed_time":1.534431421,"remaining_time":0.6086292229},
{"learn":[3.497593362],"iteration":716,"passed_time":1.535932915,"remaining_time":0.6062329358},
{"learn":[3.496291169],"iteration":717,"passed_time":1.537632684,"remaining_time":0.6039170154},
{"learn":[3.49330374],"iteration":718,"passed_time":1.539096599,"remaining_time":0.6015106319},
{"learn":[3.490044385],"iteration":719,"passed_time":1.542402834,"remaining_time":0.5998233243},
{"learn":[3.488891789],"iteration":720,"passed_time":1.546191086,"remaining_time":0.5983180485},
{"learn":[3.486869081],"iteration":721,"passed_time":1.547823174,"remaining_time":0.5959762358},
{"learn":[3.486303638],"iteration":722,"passed_time":1.549525398,"remaining_time":0.5936632578},
{"learn":[3.486035862],"iteration":723,"passed_time":1.55112206,"remaining_time":0.5913117245},
{"learn":[3.482668951],"iteration":724,"passed_time":1.553200603,"remaining_time":0.5891450563},
{"learn":[3.47820549],"iteration":725,"passed_time":1.554618343,"remaining_time":0.5867292368},
{"learn":[3.474392283],"iteration":726,"passed_time":1.557600811,"remaining_time":0.5849037433},
{"learn":[3.472268163],"iteration":727,"passed_time":1.559648252,"remaining_time":0.5827257206},
{"learn":[3.471209164],"iteration":728,"passed_time":1.562067801,"remaining_time":0.5806863841},
{"learn":[3.470049971],"iteration":729,"passed_time":1.563613386,"remaining_time":0.5783227593},
{"learn":[3.469078654],"iteration":730,"passed_time":1.565307906,"remaining_time":0.5760161788},
{"learn":[3.468643292],"iteration":731,"passed_time":1.567189105,"remaining_time":0.5737796175},
{"learn":[3.468134848],"iteration":732,"passed_time":1.568653186,"remaining_time":0.5713920881},
{"learn":[3.467820182],"iteration":733,"passed_time":1.570551895,"remaining_time":0.5691645833},
{"learn":[3.465776156],"iteration":734,"passed_time":1.572967592,"remaining_time":0.5671243698},
{"learn":[3.463037608],"iteration":735,"passed_time":1.575193497,"remaining_time":0.5650150588},
{"learn":[3.45965637],"iteration":736,"passed_time":1.577614961,"remaining_time":0.5629752168},
{"learn":[3.457275091],"iteration":737,"passed_time":1.578990435,"remaining_time":0.5605629999},
{"learn":[3.455522955],"iteration":738,"passed_time":1.580567309,"remaining_time":0.5582247192},
{"learn":[3.451270508],"iteration":739,"passed_time":1.58269743,"remaining_time":0.5560828809},
{"learn":[3.450978947],"iteration":740,"passed_time":1.584404841,"remaining_time":0.5537933251},
{"learn":[3.450608492],"iteration":741,"passed_time":1.589150019,"remaining_time":0.5525615971},
{"learn":[3.448122004],"iteration":742,"passed_time":1.593653386,"remaining_time":0.5512367702},
{"learn":[3.445646714],"iteration":743,"passed_time":1.595429846,"remaining_time":0.5489651084},
{"learn":[3.44411263],"iteration":744,"passed_time":1.597462869,"remaining_time":0.5467825928},
{"learn":[3.443264164],"iteration":745,"passed_time":1.599144121,"remaining_time":0.544480706},
{"learn":[3.439521363],"iteration":746,"passed_time":1.601591321,"remaining_time":0.5424398986},
{"learn":[3.436809225],"iteration":747,"passed_time":1.604846202,"remaining_time":0.5406701108},
{"learn":[3.435509465],"iteration":748,"passed_time":1.607718374,"remaining_time":0.5387681066},
{"learn":[3.434450277],"iteration":749,"passed_time":1.609850158,"remaining_time":0.5366167193},
{"learn":[3.431786753],"iteration":750,"passed_time":1.612079519,"remaining_time":0.5344977366},
{"learn":[3.430150302],"iteration":751,"passed_time":1.613889959,"remaining_time":0.5322403057},
{"learn":[3.42696281],"iteration":752,"passed_time":1.615516645,"remaining_time":0.5299237866},
{"learn":[3.426870334],"iteration":753,"passed_time":1.617951632,"remaining_time":0.5278728137},
{"learn":[3.425200309],"iteration":754,"passed_time":1.619573875,"remaining_time":0.5255570851},
{"learn":[3.423383783],"iteration":755,"passed_time":1.621409728,"remaining_time":0.5233121344},
{"learn":[3.422752979],"iteration":756,"passed_time":1.623343152,"remaining_time":0.5210995852},
{"learn":[3.420845924],"iteration":757,"passed_time":1.624981978,"remaining_time":0.5187937186},
{"learn":[3.418917862],"iteration":758,"passed_time":1.62684727,"remaining_time":0.5165615179},
{"learn":[3.417095735],"iteration":759,"passed_time":1.628565885,"remaining_time":0.5142839638},
{"learn":[3.414391848],"iteration":760,"passed_time":1.630099285,"remaining_time":0.5119497099},
{"learn":[3.41426711],"iteration":761,"passed_time":1.633000738,"remaining_time":0.5100448498},
{"learn":[3.411976013],"iteration":762,"passed_time":1.635398531,"remaining_time":0.507980933},
{"learn":[3.408614844],"iteration":763,"passed_time":1.639002288,"remaining_time":0.5062886649},
{"learn":[3.407906721],"iteration":764,"passed_time":1.640631616,"remaining_time":0.5039848754},
{"learn":[3.407494015],"iteration":765,"passed_time":1.643128545,"remaining_time":0.5019478844},
{"learn":[3.406287128],"iteration":766,"passed_time":1.644910322,"remaining_time":0.4996924447},
{"learn":[3.404600442],"iteration":767,"passed_time":1.647741927,"remaining_time":0.4977553737},
{"learn":[3.404012662],"iteration":768,"passed_time":1.649619417,"remaining_time":0.4955293699},
{"learn":[3.400398762],"iteration":769,"passed_time":1.652936653,"remaining_time":0.493734325},
{"learn":[3.399737714],"iteration":770,"passed_time":1.654857382,"remaining_time":0.4915205453},
{"learn":[3.399185251],"iteration":771,"passed_time":1.656529808,"remaining_time":0.489234192},
{"learn":[3.397245411],"iteration":772,"passed_time":1.658077796,"remaining_time":0.4869128844},
{"learn":[3.396229831],"iteration":773,"passed_time":1.659483373,"remaining_time":0.4845519925},
{"learn":[3.394002836],"iteration":774,"passed_time":1.661972885,"remaining_time":0.4825082569},
{"learn":[3.389617243],"iteration":775,"passed_time":1.664861134,"remaining_time":0.4805784716},
{"learn":[3.385426488],"iteration":776,"passed_time":1.669057531,"remaining_time":0.4790216595},
{"learn":[3.385072258],"iteration":777,"passed_time":1.670518846,"remaining_time":0.4766776143},
{"learn":[3.383842366],"iteration":778,"passed_time":1.672247169,"remaining_time":0.4744115846},
{"learn":[3.380110746],"iteration":779,"passed_time":1.674711139,"remaining_time":0.4723544239},
{"learn":[3.378595218],"iteration":780,"passed_time":1.677787112,"remaining_time":0.470467833},
{"learn":[3.377371219],"iteration":781,"passed_time":1.683469355,"remaining_time":0.4693047564},
{"learn":[3.375814782],"iteration":782,"passed_time":1.695777392,"remaining_time":0.4699664036},
{"learn":[3.374195887],"iteration":783,"passed_time":1.697413705,"remaining_time":0.4676547963},
{"learn":[3.373704309],"iteration":784,"passed_time":1.698866591,"remaining_time":0.4652946713},
{"learn":[3.372971757],"iteration":785,"passed_time":1.700870558,"remaining_time":0.4630868949},
{"learn":[3.371565136],"iteration":786,"passed_time":1.702500139,"remaining_time":0.4607783096},
{"learn":[3.3700309],"iteration":787,"passed_time":1.704060462,"remaining_time":0.4584528147},
{"learn":[3.368186663],"iteration":788,"passed_time":1.70568622,"remaining_time":0.4561467585},
{"learn":[3.366710398],"iteration":789,"passed_time":1.708578694,"remaining_time":0.4541791466},
{"learn":[3.364598042],"iteration":790,"passed_time":1.711819242,"remaining_time":0.4523011652},
{"learn":[3.36348442],"iteration":791,"passed_time":1.714369079,"remaining_time":0.450238344},
{"learn":[3.362001759],"iteration":792,"passed_time":1.715981422,"remaining_time":0.4479295767},
{"learn":[3.361580401],"iteration":793,"passed_time":1.717930024,"remaining_time":0.4457098048},
{"learn":[3.359543675],"iteration":794,"passed_time":1.719597137,"remaining_time":0.4434181297},
{"learn":[3.35766119],"iteration":795,"passed_time":1.721686612,"remaining_time":0.4412362674},
{"learn":[3.354592969],"iteration":796,"passed_time":1.724539843,"remaining_time":0.4392491697},
{"learn":[3.350985986],"iteration":797,"passed_time":1.727597565,"remaining_time":0.4373116644},
{"learn":[3.349589624],"iteration":798,"passed_time":1.729555467,"remaining_time":0.4350946795},
{"learn":[3.349110856],"iteration":799,"passed_time":1.731622813,"remaining_time":0.4329057032},
{"learn":[3.345315441],"iteration":800,"passed_time":1.733182976,"remaining_time":0.4305910264},
{"learn":[3.34397474],"iteration":801,"passed_time":1.734612764,"remaining_time":0.428246044},
{"learn":[3.343800902],"iteration":802,"passed_time":1.736297873,"remaining_time":0.4259659788},
{"learn":[3.342329465],"iteration":803,"passed_time":1.739315811,"remaining_time":0.4240123122},
{"learn":[3.34220347],"iteration":804,"passed_time":1.741766272,"remaining_time":0.4219185379},
{"learn":[3.341279219],"iteration":805,"passed_time":1.743736171,"remaining_time":0.4197082099},
{"learn":[3.337329521],"iteration":806,"passed_time":1.745459772,"remaining_time":0.4174395738},
{"learn":[3.336708453],"iteration":807,"passed_time":1.74691804,"remaining_time":0.4151092372},
{"learn":[3.333252703],"iteration":808,"passed_time":1.748366158,"remaining_time":0.4127786604},
{"learn":[3.332186769],"iteration":809,"passed_time":1.749740647,"remaining_time":0.4104329913},
{"learn":[3.330594851],"iteration":810,"passed_time":1.75127389,"remaining_time":0.4081267141},
{"learn":[3.327867442],"iteration":811,"passed_time":1.754380162,"remaining_time":0.4061865399},
{"learn":[3.327563111],"iteration":812,"passed_time":1.757862558,"remaining_time":0.4043300102},
{"learn":[3.326308994],"iteration":813,"passed_time":1.759316716,"remaining_time":0.4020060309},
{"learn":[3.326249879],"iteration":814,"passed_time":1.760792362,"remaining_time":0.3996890638},
{"learn":[3.322336238],"iteration":815,"passed_time":1.762612135,"remaining_time":0.3974517559},
{"learn":[3.320491154],"iteration":816,"passed_time":1.764276078,"remaining_time":0.3951805658},
{"learn":[3.320434271],"iteration":817,"passed_time":1.765719668,"remaining_time":0.3928618332},
{"learn":[3.319609638],"iteration":818,"passed_time":1.767876488,"remaining_time":0.3907028623},
{"learn":[3.316182682],"iteration":819,"passed_time":1.770269931,"remaining_time":0.3885958385},
{"learn":[3.313126612],"iteration":820,"passed_time":1.773200701,"remaining_time":0.3866052686},
{"learn":[3.311222803],"iteration":821,"passed_time":1.775828609,"remaining_time":0.3845468278},
{"learn":[3.309627335],"iteration":822,"passed_time":1.777413241,"remaining_time":0.3822626289},
{"learn":[3.307974895],"iteration":823,"passed_time":1.778863298,"remaining_time":0.3799513839},
{"learn":[3.307321505],"iteration":824,"passed_time":1.780266869,"remaining_time":0.3776323661},
{"learn":[3.306759087],"iteration":825,"passed_time":1.781954539,"remaining_time":0.3753754115},
{"learn":[3.30484037],"iteration":826,"passed_time":1.784826377,"remaining_time":0.3733675493},
{"learn":[3.30201994],"iteration":827,"passed_time":1.788629413,"remaining_time":0.3715510375},
{"learn":[3.299302297],"iteration":828,"passed_time":1.79067534,"remaining_time":0.3693672898},
{"learn":[3.298132671],"iteration":829,"passed_time":1.792486382,"remaining_time":0.367135765},
{"learn":[3.296976183],"iteration":830,"passed_time":1.794141057,"remaining_time":0.3648734521},
{"learn":[3.293144745],"iteration":831,"passed_time":1.795639614,"remaining_time":0.3625810758},
{"learn":[3.290284404],"iteration":832,"passed_time":1.79754823,"remaining_time":0.3603728144},
{"learn":[3.288285745],"iteration":833,"passed_time":1.80267902,"remaining_time":0.3588066154},
{"learn":[3.286662667],"iteration":834,"passed_time":1.805773671,"remaining_time":0.3568295279},
{"learn":[3.285692682],"iteration":835,"passed_time":1.807315776,"remaining_time":0.3545452},
{"learn":[3.284565611],"iteration":836,"passed_time":1.808943864,"remaining_time":0.3522793905},
{"learn":[3.283897383],"iteration":837,"passed_time":1.810596585,"remaining_time":0.3500198648},
{"learn":[3.280712855],"iteration":838,"passed_time":1.812198135,"remaining_time":0.3477519662},
{"learn":[3.280468341],"iteration":839,"passed_time":1.815371258,"remaining_time":0.3457850015},
{"learn":[3.277814895],"iteration":840,"passed_time":1.819720515,"remaining_time":0.344037529},
{"learn":[3.276316385],"iteration":841,"passed_time":1.821982665,"remaining_time":0.3418922341},
{"learn":[3.27557063],"iteration":842,"passed_time":1.823843604,"remaining_time":0.3396719405},
{"learn":[3.27499628],"iteration":843,"passed_time":1.825637512,"remaining_time":0.3374401088},
{"learn":[3.273569958],"iteration":844,"passed_time":1.830889959,"remaining_time":0.3358437203},
{"learn":[3.269665595],"iteration":845,"passed_time":1.833538116,"remaining_time":0.3337646215},
{"learn":[3.267984685],"iteration":846,"passed_time":1.835428108,"remaining_time":0.3315472261},
{"learn":[3.267702508],"iteration":847,"passed_time":1.838580363,"remaining_time":0.3295568575},
{"learn":[3.266671924],"iteration":848,"passed_time":1.841059883,"remaining_time":0.3274441016},
{"learn":[3.265359825],"iteration":849,"passed_time":1.845902443,"remaining_time":0.3257474899},
{"learn":[3.2618983],"iteration":850,"passed_time":1.849334954,"remaining_time":0.3237966018},
{"learn":[3.260456253],"iteration":851,"passed_time":1.85164226,"remaining_time":0.3216467776},
{"learn":[3.258389147],"iteration":852,"passed_time":1.853384138,"remaining_time":0.3193991422},
{"learn":[3.258108469],"iteration":853,"passed_time":1.857357543,"remaining_time":0.3175341936},
{"learn":[3.256424936],"iteration":854,"passed_time":1.860604895,"remaining_time":0.315541181},
{"learn":[3.254817983],"iteration":855,"passed_time":1.862694151,"remaining_time":0.3133504179},
{"learn":[3.253898449],"iteration":856,"passed_time":1.864697544,"remaining_time":0.3111455645},
{"learn":[3.253023652],"iteration":857,"passed_time":1.866505007,"remaining_time":0.3089087541},
{"learn":[3.252845542],"iteration":858,"passed_time":1.868220416,"remaining_time":0.3066578332},
{"learn":[3.252316026],"iteration":859,"passed_time":1.872541027,"remaining_time":0.3048322602},
{"learn":[3.24975301],"iteration":860,"passed_time":1.875476347,"remaining_time":0.30277725},
{"learn":[3.249151075],"iteration":861,"passed_time":1.877820685,"remaining_time":0.3006255853},
{"learn":[3.246257135],"iteration":862,"passed_time":1.879776495,"remaining_time":0.2984117959},
{"learn":[3.243826471],"iteration":863,"passed_time":1.881587553,"remaining_time":0.2961758186},
{"learn":[3.243190653],"iteration":864,"passed_time":1.883241507,"remaining_time":0.2939163046},
{"learn":[3.24008797],"iteration":865,"passed_time":1.886097773,"remaining_time":0.2918442282},
{"learn":[3.240036811],"iteration":866,"passed_time":1.891013862,"remaining_time":0.2900863249},
{"learn":[3.238676314],"iteration":867,"passed_time":1.893433028,"remaining_time":0.2879414282},
{"learn":[3.237848782],"iteration":868,"passed_time":1.895326275,"remaining_time":0.2857166192},
{"learn":[3.236405498],"iteration":869,"passed_time":1.897136341,"remaining_time":0.2834801428},
{"learn":[3.233378068],"iteration":870,"passed_time":1.898564867,"remaining_time":0.2811881376},
{"learn":[3.233169169],"iteration":871,"passed_time":1.902112991,"remaining_time":0.2792092463},
{"learn":[3.232434885],"iteration":872,"passed_time":1.905981344,"remaining_time":0.2772733456},
{"learn":[3.229978115],"iteration":873,"passed_time":1.908136212,"remaining_time":0.2750859985},
{"learn":[3.229648848],"iteration":874,"passed_time":1.910094652,"remaining_time":0.2728706646},
{"learn":[3.227208761],"iteration":875,"passed_time":1.911929828,"remaining_time":0.2706384689},
{"learn":[3.226258869],"iteration":876,"passed_time":1.913652793,"remaining_time":0.2683914408},
{"learn":[3.225331995],"iteration":877,"passed_time":1.920429383,"remaining_time":0.2668478185},
{"learn":[3.221968268],"iteration":878,"passed_time":1.924930511,"remaining_time":0.2649790579},
{"learn":[3.221166317],"iteration":879,"passed_time":1.927835596,"remaining_time":0.2628866722},
{"learn":[3.220047503],"iteration":880,"passed_time":1.929357556,"remaining_time":0.2606056176},
{"learn":[3.21982781],"iteration":881,"passed_time":1.931928166,"remaining_time":0.25846658},
{"learn":[3.216693405],"iteration":882,"passed_time":1.936351441,"remaining_time":0.2565720482},
{"learn":[3.214798761],"iteration":883,"passed_time":1.93929332,"remaining_time":0.254477404},
{"learn":[3.214395085],"iteration":884,"passed_time":1.940942526,"remaining_time":0.2522128706},
{"learn":[3.213470696],"iteration":885,"passed_time":1.945862539,"remaining_time":0.250370575},
{"learn":[3.211595017],"iteration":886,"passed_time":1.952777816,"remaining_time":0.2487755279},
{"learn":[3.210965255],"iteration":887,"passed_time":1.955363168,"remaining_time":0.2466223815},
{"learn":[3.209413583],"iteration":888,"passed_time":1.957501259,"remaining_time":0.2444124181},
{"learn":[3.208331683],"iteration":889,"passed_time":1.959782512,"remaining_time":0.2422203105},
{"learn":[3.207110711],"iteration":890,"passed_time":1.962400955,"remaining_time":0.2400692526},
{"learn":[3.204519413],"iteration":891,"passed_time":1.96606758,"remaining_time":0.2380440568},
{"learn":[3.201421296],"iteration":892,"passed_time":1.970188947,"remaining_time":0.2360696722},
{"learn":[3.200691259],"iteration":893,"passed_time":1.97254367,"remaining_time":0.2338810168},
{"learn":[3.200485067],"iteration":894,"passed_time":1.974279401,"remaining_time":0.231619371},
{"learn":[3.197467568],"iteration":895,"passed_time":1.976411175,"remaining_time":0.2294048685},
{"learn":[3.195838544],"iteration":896,"passed_time":1.982799248,"remaining_time":0.2276792894},
{"learn":[3.195671746],"iteration":897,"passed_time":1.985061267,"remaining_time":0.225474665},
{"learn":[3.194213094],"iteration":898,"passed_time":1.987112043,"remaining_time":0.2232461806},
{"learn":[3.192884691],"iteration":899,"passed_time":1.988997987,"remaining_time":0.2209997764},
{"learn":[3.188364239],"iteration":900,"passed_time":1.990727629,"remaining_time":0.2187369981},
{"learn":[3.185219478],"iteration":901,"passed_time":1.997737751,"remaining_time":0.2170491127},
{"learn":[3.184120387],"iteration":902,"passed_time":2.001052479,"remaining_time":0.2149524811},
{"learn":[3.183725321],"iteration":903,"passed_time":2.002939003,"remaining_time":0.2127014871},
{"learn":[3.181264554],"iteration":904,"passed_time":2.004528659,"remaining_time":0.2104201355},
{"learn":[3.180741589],"iteration":905,"passed_time":2.006264663,"remaining_time":0.2081554948},
{"learn":[3.179782639],"iteration":906,"passed_time":2.010041208,"remaining_time":0.2061012484},
{"learn":[3.176377564],"iteration":907,"passed_time":2.012653985,"remaining_time":0.2039252936},
{"learn":[3.174078182],"iteration":908,"passed_time":2.014353777,"remaining_time":0.2016569788},
{"learn":[3.171242379],"iteration":909,"passed_time":2.015887715,"remaining_time":0.1993735103},
{"learn":[3.170421012],"iteration":910,"passed_time":2.017541348,"remaining_time":0.1971033808},
{"learn":[3.170087224],"iteration":911,"passed_time":2.018888209,"remaining_time":0.1948050026},
{"learn":[3.167303059],"iteration":912,"passed_time":2.020556863,"remaining_time":0.1925393725},
{"learn":[3.16705966],"iteration":913,"passed_time":2.0225096,"remaining_time":0.1903017786},
{"learn":[3.165667683],"iteration":914,"passed_time":2.025558446,"remaining_time":0.1881666316},
{"learn":[3.164689733],"iteration":915,"passed_time":2.027845721,"remaining_time":0.1859596513},
{"learn":[3.163311455],"iteration":916,"passed_time":2.029825179,"remaining_time":0.1837246345},
{"learn":[3.159425016],"iteration":917,"passed_time":2.03121202,"remaining_time":0.1814372393},
{"learn":[3.159327058],"iteration":918,"passed_time":2.032452682,"remaining_time":0.1791389198},
{"learn":[3.15819426],"iteration":919,"passed_time":2.033922228,"remaining_time":0.1768628025},
{"learn":[3.157086603],"iteration":920,"passed_time":2.0369341,"remaining_time":0.1747207317},
{"learn":[3.153354154],"iteration":921,"passed_time":2.038859962,"remaining_time":0.1724848992},
{"learn":[3.153261317],"iteration":922,"passed_time":2.040733897,"remaining_time":0.1702454063},
{"learn":[3.153168454],"iteration":923,"passed_time":2.042364737,"remaining_time":0.16798671},
{"learn":[3.152080399],"iteration":924,"passed_time":2.044306154,"remaining_time":0.165754553},
{"learn":[3.151635144],"iteration":925,"passed_time":2.046614855,"remaining_time":0.163552375},
{"learn":[3.147762655],"iteration":926,"passed_time":2.050417584,"remaining_time":0.1614676199},
{"learn":[3.147172317],"iteration":927,"passed_time":2.052972336,"remaining_time":0.1592823364},
{"learn":[3.146254125],"iteration":928,"passed_time":2.054782741,"remaining_time":0.1570393699},
{"learn":[3.144869828],"iteration":929,"passed_time":2.056509437,"remaining_time":0.1547910329},
{"learn":[3.143466218],"iteration":930,"passed_time":2.058298287,"remaining_time":0.152548423},
{"learn":[3.141919643],"iteration":931,"passed_time":2.059897104,"remaining_time":0.1502929218},
{"learn":[3.141054135],"iteration":932,"passed_time":2.061524471,"remaining_time":0.1480408784},
{"learn":[3.139390417],"iteration":933,"passed_time":2.062963835,"remaining_time":0.1457768877},
{"learn":[3.139025283],"iteration":934,"passed_time":2.065764698,"remaining_time":0.1436093106},
{"learn":[3.137824183],"iteration":935,"passed_time":2.068465655,"remaining_time":0.141433549},
{"learn":[3.135620453],"iteration":936,"passed_time":2.070237479,"remaining_time":0.1391941955},
{"learn":[3.13443178],"iteration":937,"passed_time":2.0715997,"remaining_time":0.1369287648},
{"learn":[3.132765713],"iteration":938,"passed_time":2.072947597,"remaining_time":0.1346643274},
{"learn":[3.131434124],"iteration":939,"passed_time":2.074253272,"remaining_time":0.132399145},
{"learn":[3.128384262],"iteration":940,"passed_time":2.075512727,"remaining_time":0.130133104},
{"learn":[3.128120455],"iteration":941,"passed_time":2.076895638,"remaining_time":0.1278768015},
{"learn":[3.126314615],"iteration":942,"passed_time":2.078229865,"remaining_time":0.1256194086},
{"learn":[3.125409666],"iteration":943,"passed_time":2.080778371,"remaining_time":0.1234360051},
{"learn":[3.123072589],"iteration":944,"passed_time":2.082378302,"remaining_time":0.1211966208},
{"learn":[3.122921099],"iteration":945,"passed_time":2.083758796,"remaining_time":0.1189460624},
{"learn":[3.122182662],"iteration":946,"passed_time":2.085210497,"remaining_time":0.1167013266},
{"learn":[3.120040951],"iteration":947,"passed_time":2.086783942,"remaining_time":0.114464942},
{"learn":[3.118767799],"iteration":948,"passed_time":2.088415436,"remaining_time":0.112233074},
{"learn":[3.118203218],"iteration":949,"passed_time":2.089861385,"remaining_time":0.1099927045},
{"learn":[3.116343362],"iteration":950,"passed_time":2.09143241,"remaining_time":0.1077604501},
{"learn":[3.11480829],"iteration":951,"passed_time":2.093537193,"remaining_time":0.1055564971},
{"learn":[3.112607903],"iteration":952,"passed_time":2.096477857,"remaining_time":0.1033939762},
{"learn":[3.111661241],"iteration":953,"passed_time":2.098775024,"remaining_time":0.1011987957},
{"learn":[3.110249676],"iteration":954,"passed_time":2.101067275,"remaining_time":0.09900317001},
{"learn":[3.107333579],"iteration":955,"passed_time":2.102431785,"remaining_time":0.09676464282},
{"learn":[3.107149851],"iteration":956,"passed_time":2.103632895,"remaining_time":0.09452060032},
{"learn":[3.106867336],"iteration":957,"passed_time":2.1050347,"remaining_time":0.09228753381},
{"learn":[3.10364681],"iteration":958,"passed_time":2.106973745,"remaining_time":0.09007916948},
{"learn":[3.102703811],"iteration":959,"passed_time":2.10891112,"remaining_time":0.08787129666},
{"learn":[3.101469264],"iteration":960,"passed_time":2.112136266,"remaining_time":0.08571624806},
{"learn":[3.09863569],"iteration":961,"passed_time":2.113821281,"remaining_time":0.08349813792},
{"learn":[3.09645939],"iteration":962,"passed_time":2.115198614,"remaining_time":0.0812693133},
{"learn":[3.096240186],"iteration":963,"passed_time":2.116488966,"remaining_time":0.07903900703},
{"learn":[3.094838828],"iteration":964,"passed_time":2.117791592,"remaining_time":0.07681109401},
{"learn":[3.094176802],"iteration":965,"passed_time":2.119079989,"remaining_time":0.07458459587},
{"learn":[3.093182279],"iteration":966,"passed_time":2.120852563,"remaining_time":0.07237656109},
{"learn":[3.090150687],"iteration":967,"passed_time":2.122281473,"remaining_time":0.07015806522},
{"learn":[3.088612829],"iteration":968,"passed_time":2.123839275,"remaining_time":0.06794532252},
{"learn":[3.087153684],"iteration":969,"passed_time":2.127015374,"remaining_time":0.06578398065},
{"learn":[3.085866843],"iteration":970,"passed_time":2.128668815,"remaining_time":0.06357507275},
{"learn":[3.082669094],"iteration":971,"passed_time":2.130014288,"remaining_time":0.06135843629},
{"learn":[3.081047548],"iteration":972,"passed_time":2.131286007,"remaining_time":0.05914154386},
{"learn":[3.079684322],"iteration":973,"passed_time":2.132899827,"remaining_time":0.05693572434},
{"learn":[3.07613431],"iteration":974,"passed_time":2.134412812,"remaining_time":0.05472853363},
{"learn":[3.074005935],"iteration":975,"passed_time":2.135804398,"remaining_time":0.05251978029},
{"learn":[3.072988853],"iteration":976,"passed_time":2.137129275,"remaining_time":0.05031112931},
{"learn":[3.072344268],"iteration":977,"passed_time":2.138473639,"remaining_time":0.04810472399},
{"learn":[3.070654438],"iteration":978,"passed_time":2.140422233,"remaining_time":0.04591304075},
{"learn":[3.069724506],"iteration":979,"passed_time":2.143052156,"remaining_time":0.04373575828},
{"learn":[3.067763166],"iteration":980,"passed_time":2.144488381,"remaining_time":0.04153443348},
{"learn":[3.066737893],"iteration":981,"passed_time":2.145780334,"remaining_time":0.03933202242},
{"learn":[3.065248174],"iteration":982,"passed_time":2.14709803,"remaining_time":0.03713190896},
{"learn":[3.063186837],"iteration":983,"passed_time":2.14879295,"remaining_time":0.03493972277},
{"learn":[3.062880371],"iteration":984,"passed_time":2.150183988,"remaining_time":0.03274391861},
{"learn":[3.061288645],"iteration":985,"passed_time":2.151625725,"remaining_time":0.03055046668},
{"learn":[3.059970575],"iteration":986,"passed_time":2.152983924,"remaining_time":0.0283574377},
{"learn":[3.059576341],"iteration":987,"passed_time":2.154238073,"remaining_time":0.0261648349},
{"learn":[3.058175919],"iteration":988,"passed_time":2.156772497,"remaining_time":0.02398836953},
{"learn":[3.056830702],"iteration":989,"passed_time":2.15834384,"remaining_time":0.02180145293},
{"learn":[3.056336579],"iteration":990,"passed_time":2.159825985,"remaining_time":0.01961496858},
{"learn":[3.055810414],"iteration":991,"passed_time":2.161422643,"remaining_time":0.01743082776},
{"learn":[3.055476518],"iteration":992,"passed_time":2.162832424,"remaining_time":0.01524655284},
{"learn":[3.053331734],"iteration":993,"passed_time":2.164392797,"remaining_time":0.01306474526},
{"learn":[3.050890374],"iteration":994,"passed_time":2.165763408,"remaining_time":0.01088323321},
{"learn":[3.04972623],"iteration":995,"passed_time":2.167053648,"remaining_time":0.008703026698},
{"learn":[3.047217327],"iteration":996,"passed_time":2.168744322,"remaining_time":0.006525810398},
{"learn":[3.047155483],"iteration":997,"passed_time":2.170003722,"remaining_time":0.004348704853},
{"learn":[3.04430671],"iteration":998,"passed_time":2.173208271,"remaining_time":0.002175383655},
{"learn":[3.042664195],"iteration":999,"passed_time":2.175243873,"remaining_time":0}
]}